config.cpython-312.pyc (Python 3.12)
[Code]
    File Name: /code/NeMo/nemo/collections/speechlm2/vllm/nemotron_v3/config.py
    Object Name: <module>
    Qualified Name: <module>
    Arg Count: 0
    Pos Only Arg Count: 0
    KW Only Arg Count: 0
    Stack Size: 5
    Flags: 0x00000000
    [Names]
        '__doc__'
        'transformers'
        'AutoConfig'
        'PretrainedConfig'
        'NeMoSpeechLMConfig'
    [Locals+Names]
    [Constants]
        "Configuration for NeMo Speech LM models in vLLM.\n\nProvides ``NeMoSpeechLMConfig``, a HuggingFace-compatible config class\nthat wraps the LLM backbone's text config with NeMo-specific fields\n(perception, audio_locator_tag, etc.).  The checkpoint's ``config.json``\ndetermines which LLM backbone and encoder are used.\n"
        0
        (
            'AutoConfig'
            'PretrainedConfig'
        )
        [Code]
            File Name: /code/NeMo/nemo/collections/speechlm2/vllm/nemotron_v3/config.py
            Object Name: NeMoSpeechLMConfig
            Qualified Name: NeMoSpeechLMConfig
            Arg Count: 0
            Pos Only Arg Count: 0
            KW Only Arg Count: 0
            Stack Size: 16
            Flags: 0x00000000
            [Names]
                '__name__'
                '__module__'
                '__qualname__'
                '__doc__'
                'model_type'
                'dict'
                'str'
                'bool'
                '__init__'
                'PretrainedConfig'
                'get_text_config'
                '_ATTR_ALIASES'
                '__getattr__'
                '__classcell__'
            [Locals+Names]
                '__class__'
            [Constants]
                'NeMoSpeechLMConfig'
                'HuggingFace config for NeMo Speech LM multimodal models.\n\n    Wraps a pretrained LLM config (e.g. NemotronH, Qwen3) with\n    additional fields for the speech perception module.  The LLM\n    backbone config is loaded from ``pretrained_llm`` at init time.\n    '
                'nemo_speechlm'
                None
                'perception'
                'pretrained_llm'
                'pretrained_asr'
                'audio_locator_tag'
                'prompt_format'
                'pretrained_weights'
                'pe_encoder_path'
                [Code]
                    File Name: /code/NeMo/nemo/collections/speechlm2/vllm/nemotron_v3/config.py
                    Object Name: __init__
                    Qualified Name: NeMoSpeechLMConfig.__init__
                    Arg Count: 8
                    Pos Only Arg Count: 0
                    KW Only Arg Count: 0
                    Stack Size: 5
                    Flags: 0x0000000B (CO_OPTIMIZED | CO_NEWLOCALS | CO_VARKEYWORDS)
                    [Names]
                        'super'
                        '__init__'
                        'perception'
                        'pretrained_llm'
                        'pretrained_asr'
                        'audio_locator_tag'
                        'prompt_format'
                        'pretrained_weights'
                        'pe_encoder_path'
                        'AutoConfig'
                        'from_pretrained'
                        'text_config'
                        'architectures'
                        'hasattr'
                        'total_num_kv_heads'
                        'getattr'
                        'rms_norm_eps'
                        'vocab_size'
                    [Locals+Names]
                        'self'
                        'perception'
                        'pretrained_llm'
                        'pretrained_asr'
                        'audio_locator_tag'
                        'prompt_format'
                        'pretrained_weights'
                        'pe_encoder_path'
                        'kwargs'
                        '__class__'
                    [Constants]
                        None
                        True
                        (
                            'trust_remote_code'
                        )
                        'NemotronHForCausalLM'
                        'total_num_kv_heads'
                        'num_key_value_heads'
                        2
                        'rms_norm_eps'
                        'layer_norm_epsilon'
                        1e-05
                        10
                        (
                        )
                    [Disassembly]
                        0       COPY_FREE_VARS                  1
                        2       RESUME                          0
                        4       LOAD_GLOBAL                     1: NULL + super
                        14      LOAD_DEREF                      9: __class__
                        16      LOAD_FAST                       0: self
                        18      LOAD_SUPER_ATTR                 4: __init__
                        22      LOAD_CONST                      11: ()
                        24      BUILD_MAP                       0
                        26      LOAD_FAST                       8: kwargs
                        28      DICT_MERGE                      1
                        30      CALL_FUNCTION_EX                1
                        32      POP_TOP                         
                        34      LOAD_FAST                       1: perception
                        36      COPY                            1
                        38      POP_JUMP_IF_TRUE                2 (to 44)
                        40      POP_TOP                         
                        42      BUILD_MAP                       0
                        44      LOAD_FAST                       0: self
                        46      STORE_ATTR                      2: perception
                        56      LOAD_FAST                       2: pretrained_llm
                        58      LOAD_FAST                       0: self
                        60      STORE_ATTR                      3: pretrained_llm
                        70      LOAD_FAST                       3: pretrained_asr
                        72      LOAD_FAST                       0: self
                        74      STORE_ATTR                      4: pretrained_asr
                        84      LOAD_FAST                       4: audio_locator_tag
                        86      LOAD_FAST                       0: self
                        88      STORE_ATTR                      5: audio_locator_tag
                        98      LOAD_FAST                       5: prompt_format
                        100     LOAD_FAST                       0: self
                        102     STORE_ATTR                      6: prompt_format
                        112     LOAD_FAST                       6: pretrained_weights
                        114     LOAD_FAST                       0: self
                        116     STORE_ATTR                      7: pretrained_weights
                        126     LOAD_FAST                       7: pe_encoder_path
                        128     LOAD_FAST                       0: self
                        130     STORE_ATTR                      8: pe_encoder_path
                        140     LOAD_GLOBAL                     19: NULL + AutoConfig
                        150     LOAD_ATTR                       20: from_pretrained
                        170     LOAD_FAST                       2: pretrained_llm
                        172     LOAD_CONST                      1: True
                        174     KW_NAMES                        2: ('trust_remote_code',)
                        176     CALL                            2
                        184     LOAD_FAST                       0: self
                        186     STORE_ATTR                      11: text_config
                        196     LOAD_CONST                      3: 'NemotronHForCausalLM'
                        198     BUILD_LIST                      1
                        200     LOAD_FAST                       0: self
                        202     LOAD_ATTR                       22: text_config
                        222     STORE_ATTR                      12: architectures
                        232     LOAD_GLOBAL                     27: NULL + hasattr
                        242     LOAD_FAST                       0: self
                        244     LOAD_ATTR                       22: text_config
                        264     LOAD_CONST                      4: 'total_num_kv_heads'
                        266     CALL                            2
                        274     POP_JUMP_IF_FALSE               22 (to 320)
                        276     LOAD_FAST                       0: self
                        278     LOAD_ATTR                       22: text_config
                        298     LOAD_ATTR                       28: total_num_kv_heads
                        318     POP_JUMP_IF_NOT_NONE            38 (to 396)
                        320     LOAD_GLOBAL                     31: NULL + getattr
                        330     LOAD_FAST                       0: self
                        332     LOAD_ATTR                       22: text_config
                        352     LOAD_CONST                      5: 'num_key_value_heads'
                        354     LOAD_CONST                      6: 2
                        356     CALL                            3
                        364     LOAD_FAST                       0: self
                        366     LOAD_ATTR                       22: text_config
                        386     STORE_ATTR                      14: total_num_kv_heads
                        396     LOAD_GLOBAL                     27: NULL + hasattr
                        406     LOAD_FAST                       0: self
                        408     LOAD_ATTR                       22: text_config
                        428     LOAD_CONST                      7: 'rms_norm_eps'
                        430     CALL                            2
                        438     POP_JUMP_IF_TRUE                38 (to 516)
                        440     LOAD_GLOBAL                     31: NULL + getattr
                        450     LOAD_FAST                       0: self
                        452     LOAD_ATTR                       22: text_config
                        472     LOAD_CONST                      8: 'layer_norm_epsilon'
                        474     LOAD_CONST                      9: 1e-05
                        476     CALL                            3
                        484     LOAD_FAST                       0: self
                        486     LOAD_ATTR                       22: text_config
                        506     STORE_ATTR                      16: rms_norm_eps
                        516     LOAD_FAST                       0: self
                        518     LOAD_ATTR                       22: text_config
                        538     LOAD_ATTR                       34: vocab_size
                        558     LOAD_CONST                      10: 10
                        560     BINARY_OP                       0 (+)
                        564     LOAD_FAST                       0: self
                        566     LOAD_ATTR                       22: text_config
                        586     STORE_ATTR                      17: vocab_size
                        596     RETURN_CONST                    0: None
                    [Exception Table]
                'return'
                [Code]
                    File Name: /code/NeMo/nemo/collections/speechlm2/vllm/nemotron_v3/config.py
                    Object Name: get_text_config
                    Qualified Name: NeMoSpeechLMConfig.get_text_config
                    Arg Count: 2
                    Pos Only Arg Count: 0
                    KW Only Arg Count: 0
                    Stack Size: 1
                    Flags: 0x00000003 (CO_OPTIMIZED | CO_NEWLOCALS)
                    [Names]
                        'text_config'
                    [Locals+Names]
                        'self'
                        'decoder'
                    [Constants]
                        "Return the LLM backbone's text config."
                    [Disassembly]
                        0       RESUME                          0
                        2       LOAD_FAST                       0: self
                        4       LOAD_ATTR                       0: text_config
                        24      RETURN_VALUE                    
                    [Exception Table]
                'layer_norm_epsilon'
                (
                    'rms_norm_eps'
                    'layer_norm_eps'
                )
                [Code]
                    File Name: /code/NeMo/nemo/collections/speechlm2/vllm/nemotron_v3/config.py
                    Object Name: __getattr__
                    Qualified Name: NeMoSpeechLMConfig.__getattr__
                    Arg Count: 2
                    Pos Only Arg Count: 0
                    KW Only Arg Count: 0
                    Stack Size: 8
                    Flags: 0x00000003 (CO_OPTIMIZED | CO_NEWLOCALS)
                    [Names]
                        'startswith'
                        'AttributeError'
                        '_ATTR_ALIASES'
                        'get'
                        'getattr'
                        'text_config'
                        'type'
                        '__name__'
                    [Locals+Names]
                        'self'
                        'name'
                        'alias'
                    [Constants]
                        None
                        '_'
                        (
                            'perception'
                            'pretrained_llm'
                            'pretrained_asr'
                            'audio_locator_tag'
                            'prompt_format'
                            'pretrained_weights'
                            'pe_encoder_path'
                            'text_config'
                            '_ATTR_ALIASES'
                        )
                        "'"
                        "' has no attribute '"
                    [Disassembly]
                        0       RESUME                          0
                        2       LOAD_FAST                       1: name
                        4       LOAD_ATTR                       1: startswith
                        24      LOAD_CONST                      1: '_'
                        26      CALL                            1
                        34      POP_JUMP_IF_TRUE                4 (to 44)
                        36      LOAD_FAST                       1: name
                        38      LOAD_CONST                      2: ('perception', 'pretrained_llm', 'pretrained_asr', 'audio_locator_tag', 'prompt_format', 'pretrained_weights', 'pe_encoder_path', 'text_config', '_ATTR_ALIASES')
                        40      CONTAINS_OP                     0 (in)
                        42      POP_JUMP_IF_FALSE               11 (to 66)
                        44      LOAD_GLOBAL                     3: NULL + AttributeError
                        54      LOAD_FAST                       1: name
                        56      CALL                            1
                        64      RAISE_VARARGS                   1
                        66      LOAD_FAST                       0: self
                        68      LOAD_ATTR                       4: _ATTR_ALIASES
                        88      LOAD_ATTR                       7: get
                        108     LOAD_FAST                       1: name
                        110     LOAD_FAST                       1: name
                        112     CALL                            2
                        120     STORE_FAST                      2: alias
                        122     NOP                             
                        124     LOAD_GLOBAL                     9: NULL + getattr
                        134     LOAD_FAST                       0: self
                        136     LOAD_ATTR                       10: text_config
                        156     LOAD_FAST                       2: alias
                        158     CALL                            2
                        166     RETURN_VALUE                    
                        168     PUSH_EXC_INFO                   
                        170     LOAD_GLOBAL                     2: AttributeError
                        180     CHECK_EXC_MATCH                 
                        182     POP_JUMP_IF_FALSE               83 (to 350)
                        184     POP_TOP                         
                        186     LOAD_FAST                       2: alias
                        188     LOAD_FAST                       1: name
                        190     COMPARE_OP                      55 (!=)
                        194     POP_JUMP_IF_FALSE               40 (to 276)
                        196     NOP                             
                        198     LOAD_GLOBAL                     9: NULL + getattr
                        208     LOAD_FAST                       0: self
                        210     LOAD_ATTR                       10: text_config
                        230     LOAD_FAST                       1: name
                        232     CALL                            2
                        240     SWAP                            2
                        242     POP_EXCEPT                      
                        244     RETURN_VALUE                    
                        246     PUSH_EXC_INFO                   
                        248     LOAD_GLOBAL                     2: AttributeError
                        258     CHECK_EXC_MATCH                 
                        260     POP_JUMP_IF_FALSE               3 (to 268)
                        262     POP_TOP                         
                        264     POP_EXCEPT                      
                        266     JUMP_FORWARD                    4 (to 276)
                        268     RERAISE                         0
                        270     COPY                            3
                        272     POP_EXCEPT                      
                        274     RERAISE                         1
                        276     LOAD_GLOBAL                     3: NULL + AttributeError
                        286     LOAD_CONST                      3: "'"
                        288     LOAD_GLOBAL                     13: NULL + type
                        298     LOAD_FAST                       0: self
                        300     CALL                            1
                        308     LOAD_ATTR                       14: __name__
                        328     FORMAT_VALUE                    0 (FVC_NONE)
                        330     LOAD_CONST                      4: "' has no attribute '"
                        332     LOAD_FAST                       1: name
                        334     FORMAT_VALUE                    0 (FVC_NONE)
                        336     LOAD_CONST                      3: "'"
                        338     BUILD_STRING                    5
                        340     CALL                            1
                        348     RAISE_VARARGS                   1
                        350     RERAISE                         0
                        352     COPY                            3
                        354     POP_EXCEPT                      
                        356     RERAISE                         1
                    [Exception Table]
                        124 to 166 -> 168 [0] 
                        168 to 196 -> 352 [1] lasti
                        198 to 240 -> 246 [1] 
                        240 to 242 -> 352 [1] lasti
                        246 to 264 -> 270 [2] lasti
                        264 to 268 -> 352 [1] lasti
                        268 to 270 -> 270 [2] lasti
                        270 to 352 -> 352 [1] lasti
                (
                    None
                    'nvidia/NVIDIA-Nemotron-3-Nano-30B-A3B-BF16'
                    'nvidia/canary-1b-v2'
                    '<|audio|>'
                    'nemotron-nano-v3'
                    True
                    None
                )
                (
                    False
                )
            [Disassembly]
                0       MAKE_CELL                       0: __class__
                2       RESUME                          0
                4       LOAD_NAME                       0: __name__
                6       STORE_NAME                      1: __module__
                8       LOAD_CONST                      0: 'NeMoSpeechLMConfig'
                10      STORE_NAME                      2: __qualname__
                12      LOAD_CONST                      1: 'HuggingFace config for NeMo Speech LM multimodal models.\n\n    Wraps a pretrained LLM config (e.g. NemotronH, Qwen3) with\n    additional fields for the speech perception module.  The LLM\n    backbone config is loaded from ``pretrained_llm`` at init time.\n    '
                14      STORE_NAME                      3: __doc__
                16      LOAD_CONST                      2: 'nemo_speechlm'
                18      STORE_NAME                      4: model_type
                20      NOP                             
                22      NOP                             
                24      NOP                             
                26      NOP                             
                28      NOP                             
                30      NOP                             
                32      NOP                             
                34      LOAD_CONST                      17: (None, 'nvidia/NVIDIA-Nemotron-3-Nano-30B-A3B-BF16', 'nvidia/canary-1b-v2', '<|audio|>', 'nemotron-nano-v3', True, None)
                36      LOAD_CONST                      4: 'perception'
                38      LOAD_NAME                       5: dict
                40      LOAD_CONST                      3: None
                42      BINARY_OP                       7 (|)
                46      LOAD_CONST                      5: 'pretrained_llm'
                48      LOAD_NAME                       6: str
                50      LOAD_CONST                      6: 'pretrained_asr'
                52      LOAD_NAME                       6: str
                54      LOAD_CONST                      7: 'audio_locator_tag'
                56      LOAD_NAME                       6: str
                58      LOAD_CONST                      8: 'prompt_format'
                60      LOAD_NAME                       6: str
                62      LOAD_CONST                      9: 'pretrained_weights'
                64      LOAD_NAME                       7: bool
                66      LOAD_CONST                      10: 'pe_encoder_path'
                68      LOAD_NAME                       6: str
                70      LOAD_CONST                      3: None
                72      BINARY_OP                       7 (|)
                76      BUILD_TUPLE                     14
                78      LOAD_CLOSURE                    0: __class__
                80      BUILD_TUPLE                     1
                82      LOAD_CONST                      11: <CODE> __init__
                84      MAKE_FUNCTION                   13
                86      STORE_NAME                      8: __init__
                88      LOAD_CONST                      18: (False,)
                90      LOAD_CONST                      12: 'return'
                92      LOAD_NAME                       9: PretrainedConfig
                94      BUILD_TUPLE                     2
                96      LOAD_CONST                      13: <CODE> get_text_config
                98      MAKE_FUNCTION                   5
                100     STORE_NAME                      10: get_text_config
                102     LOAD_CONST                      14: 'layer_norm_epsilon'
                104     LOAD_CONST                      14: 'layer_norm_epsilon'
                106     LOAD_CONST                      15: ('rms_norm_eps', 'layer_norm_eps')
                108     BUILD_CONST_KEY_MAP             2
                110     STORE_NAME                      11: _ATTR_ALIASES
                112     LOAD_CONST                      16: <CODE> __getattr__
                114     MAKE_FUNCTION                   0
                116     STORE_NAME                      12: __getattr__
                118     LOAD_CLOSURE                    0: __class__
                120     COPY                            1
                122     STORE_NAME                      13: __classcell__
                124     RETURN_VALUE                    
            [Exception Table]
        'NeMoSpeechLMConfig'
        None
    [Disassembly]
        0       RESUME                          0
        2       LOAD_CONST                      0: "Configuration for NeMo Speech LM models in vLLM.\n\nProvides ``NeMoSpeechLMConfig``, a HuggingFace-compatible config class\nthat wraps the LLM backbone's text config with NeMo-specific fields\n(perception, audio_locator_tag, etc.).  The checkpoint's ``config.json``\ndetermines which LLM backbone and encoder are used.\n"
        4       STORE_NAME                      0: __doc__
        6       LOAD_CONST                      1: 0
        8       LOAD_CONST                      2: ('AutoConfig', 'PretrainedConfig')
        10      IMPORT_NAME                     1: transformers
        12      IMPORT_FROM                     2: AutoConfig
        14      STORE_NAME                      2: AutoConfig
        16      IMPORT_FROM                     3: PretrainedConfig
        18      STORE_NAME                      3: PretrainedConfig
        20      POP_TOP                         
        22      PUSH_NULL                       
        24      LOAD_BUILD_CLASS                
        26      LOAD_CONST                      3: <CODE> NeMoSpeechLMConfig
        28      MAKE_FUNCTION                   0
        30      LOAD_CONST                      4: 'NeMoSpeechLMConfig'
        32      LOAD_NAME                       3: PretrainedConfig
        34      CALL                            3
        42      STORE_NAME                      4: NeMoSpeechLMConfig
        44      RETURN_CONST                    5: None
    [Exception Table]
