model.cpython-312.pyc (Python 3.12)
[Code]
    File Name: /code/NeMo/nemo/collections/speechlm2/vllm/nemotron_v3/model.py
    Object Name: <module>
    Qualified Name: <module>
    Arg Count: 0
    Pos Only Arg Count: 0
    KW Only Arg Count: 0
    Stack Size: 10
    Flags: 0x00000000
    [Names]
        '__doc__'
        're'
        'collections.abc'
        'Iterable'
        'Mapping'
        'typing'
        'Annotated'
        'Literal'
        'torch'
        'nn'
        'transformers'
        'BatchFeature'
        'vllm.config'
        'VllmConfig'
        'vllm.config.multimodal'
        'BaseDummyOptions'
        'vllm.model_executor.models.interfaces'
        'IsHybrid'
        'MultiModalEmbeddings'
        'SupportsMambaPrefixCaching'
        'SupportsMultiModal'
        'SupportsPP'
        'vllm.model_executor.models.module_mapping'
        'MultiModelKeys'
        'vllm.model_executor.models.utils'
        'AutoWeightsLoader'
        'init_vllm_registered_model'
        'maybe_prefix'
        'vllm.multimodal'
        'MULTIMODAL_REGISTRY'
        'vllm.inputs'
        'MultiModalDataDict'
        'vllm.multimodal.inputs'
        'MultiModalFieldConfig'
        'MultiModalKwargsItems'
        'vllm.multimodal.parse'
        'AudioProcessorItems'
        'MultiModalDataItems'
        'MultiModalDataParser'
        'vllm.multimodal.processing'
        'BaseMultiModalProcessor'
        'BaseProcessingInfo'
        'PromptReplacement'
        'PromptUpdate'
        'PromptUpdateDetails'
        'vllm.multimodal.processing.dummy_inputs'
        'BaseDummyInputsBuilder'
        'vllm.sequence'
        'IntermediateTensors'
        'vllm.utils.tensor_schema'
        'TensorSchema'
        'TensorShape'
        '_AUDIO_PLACEHOLDER'
        '_SAMPLING_RATE'
        '_MAX_AUDIO_DURATION_S'
        '_ensure_special_tokens'
        'Module'
        'str'
        '_mount_parallel_expert_encoder'
        'dict'
        'int'
        '_load_nemo_perception'
        'NeMoSpeechLMAudioInputs'
        'NeMoSpeechLMProcessingInfo'
        'NeMoSpeechLMMultiModalProcessor'
        'NeMoSpeechLMDummyInputsBuilder'
        'register_processor'
        'NeMoSpeechLMForConditionalGeneration'
    [Locals+Names]
    [Constants]
        'Inference-only NeMo Speech LM model for vLLM.\n\nArchitecture: NeMo speech encoder (e.g. FastConformer) + projection + LLM backbone\n(e.g. NemotronH).  Requires NeMo toolkit for the audio encoder:\n``pip install nemo_toolkit[asr]``\n'
        0
        None
        (
            'Iterable'
            'Mapping'
        )
        (
            'Annotated'
            'Literal'
        )
        (
            'nn'
        )
        (
            'BatchFeature'
        )
        (
            'VllmConfig'
        )
        (
            'BaseDummyOptions'
        )
        (
            'IsHybrid'
            'MultiModalEmbeddings'
            'SupportsMambaPrefixCaching'
            'SupportsMultiModal'
            'SupportsPP'
        )
        (
            'MultiModelKeys'
        )
        (
            'AutoWeightsLoader'
            'init_vllm_registered_model'
            'maybe_prefix'
        )
        (
            'MULTIMODAL_REGISTRY'
        )
        (
            'MultiModalDataDict'
        )
        (
            'MultiModalFieldConfig'
            'MultiModalKwargsItems'
        )
        (
            'AudioProcessorItems'
            'MultiModalDataItems'
            'MultiModalDataParser'
        )
        (
            'BaseMultiModalProcessor'
            'BaseProcessingInfo'
            'PromptReplacement'
            'PromptUpdate'
            'PromptUpdateDetails'
        )
        (
            'BaseDummyInputsBuilder'
        )
        (
            'IntermediateTensors'
        )
        (
            'TensorSchema'
            'TensorShape'
        )
        '<|audio|>'
        16000
        40
        [Code]
            File Name: /code/NeMo/nemo/collections/speechlm2/vllm/nemotron_v3/model.py
            Object Name: _ensure_special_tokens
            Qualified Name: _ensure_special_tokens
            Arg Count: 1
            Pos Only Arg Count: 0
            KW Only Arg Count: 0
            Stack Size: 5
            Flags: 0x00000003 (CO_OPTIMIZED | CO_NEWLOCALS)
            [Names]
                '_AUDIO_PLACEHOLDER'
                'set'
                'get_vocab'
                'keys'
                'add_special_tokens'
            [Locals+Names]
                'tokenizer'
                'special'
                'existing'
                't'
                'to_add'
            [Constants]
                None
                'additional_special_tokens'
            [Disassembly]
                0       RESUME                          0
                2       LOAD_GLOBAL                     0: _AUDIO_PLACEHOLDER
                12      BUILD_LIST                      1
                14      STORE_FAST                      1: special
                16      LOAD_GLOBAL                     3: NULL + set
                26      LOAD_FAST                       0: tokenizer
                28      LOAD_ATTR                       5: get_vocab
                48      CALL                            0
                56      LOAD_ATTR                       7: keys
                76      CALL                            0
                84      CALL                            1
                92      STORE_FAST                      2: existing
                94      LOAD_FAST                       1: special
                96      GET_ITER                        
                98      LOAD_FAST_AND_CLEAR             3: t
                100     SWAP                            2
                102     BUILD_LIST                      0
                104     SWAP                            2
                106     FOR_ITER                        9 (to 126)
                110     STORE_FAST                      3: t
                112     LOAD_FAST                       3: t
                114     LOAD_FAST                       2: existing
                116     CONTAINS_OP                     1 (not in)
                118     POP_JUMP_IF_TRUE                1 (to 122)
                120     JUMP_BACKWARD                   8 (to 106)
                122     LOAD_FAST                       3: t
                124     LIST_APPEND                     2
                126     JUMP_BACKWARD                   11 (to 106)
                128     END_FOR                         
                130     STORE_FAST                      4: to_add
                132     STORE_FAST                      3: t
                134     LOAD_FAST                       4: to_add
                136     POP_JUMP_IF_FALSE               20 (to 178)
                138     LOAD_FAST                       0: tokenizer
                140     LOAD_ATTR                       9: add_special_tokens
                160     LOAD_CONST                      1: 'additional_special_tokens'
                162     LOAD_FAST                       4: to_add
                164     BUILD_MAP                       1
                166     CALL                            1
                174     POP_TOP                         
                176     RETURN_CONST                    0: None
                178     RETURN_CONST                    0: None
                180     SWAP                            2
                182     POP_TOP                         
                184     SWAP                            2
                186     STORE_FAST                      3: t
                188     RERAISE                         0
            [Exception Table]
                102 to 120 -> 180 [2] 
                122 to 130 -> 180 [2] 
        'perception'
        'pe_encoder_path'
        'return'
        [Code]
            File Name: /code/NeMo/nemo/collections/speechlm2/vllm/nemotron_v3/model.py
            Object Name: _mount_parallel_expert_encoder
            Qualified Name: _mount_parallel_expert_encoder
            Arg Count: 2
            Pos Only Arg Count: 0
            KW Only Arg Count: 0
            Stack Size: 7
            Flags: 0x00000003 (CO_OPTIMIZED | CO_NEWLOCALS)
            [Names]
                'nemo.collections.asr.modules.parallel_expert_encoder'
                'is_parallel_expert_encoder_nemo'
                'load_parallel_expert_encoder_from_nemo'
                'ValueError'
                'getattr'
                'RuntimeError'
                'int'
                'd_model'
                'preprocessor'
                'featurizer'
                'normalize'
                'AttributeError'
                'encoder'
            [Locals+Names]
                'perception'
                'pe_encoder_path'
                'is_parallel_expert_encoder_nemo'
                'load_parallel_expert_encoder_from_nemo'
                'pe_encoder'
                'existing_encoder'
                'existing_d_model'
            [Constants]
                'Replace ``perception.encoder`` with a ParallelExpertEncoder loaded from a\n    self-contained PE ``.nemo`` bundle.\n\n    Mirrors training-time ``setup_parallel_expert_encoder`` in\n    nemo/collections/speechlm2/parts/pretrained.py:\n      1. Validate the bundle is a ParallelExpertEncoderPT.\n      2. Load the ParallelExpertEncoder (asr_encoder + diarization_model +\n         asr_norm + diar_norm + diar_kernel buffer).\n      3. Sanity-check d_model matches the existing single-encoder slot the\n         AudioPerceptionModule built (so perception.proj stays compatible).\n      4. Disable preprocessor featurizer normalization -- PE expects\n         un-normalised mels and replays ASR normalisation internally.\n    '
                0
                (
                    'is_parallel_expert_encoder_nemo'
                    'load_parallel_expert_encoder_from_nemo'
                )
                'pe_encoder_path='
                ' is not a ParallelExpertEncoderPT .nemo bundle.'
                'cpu'
                True
                (
                    'map_location'
                    'strict'
                )
                'encoder'
                None
                'perception module has no `encoder` attribute to replace with the PE bundle.'
                'd_model'
                -1
                'ParallelExpertEncoder d_model='
                ' does not match the existing perception encoder d_model='
                '.'
            [Disassembly]
                0       RESUME                          0
                2       LOAD_CONST                      1: 0
                4       LOAD_CONST                      2: ('is_parallel_expert_encoder_nemo', 'load_parallel_expert_encoder_from_nemo')
                6       IMPORT_NAME                     0: nemo.collections.asr.modules.parallel_expert_encoder
                8       IMPORT_FROM                     1: is_parallel_expert_encoder_nemo
                10      STORE_FAST                      2: is_parallel_expert_encoder_nemo
                12      IMPORT_FROM                     2: load_parallel_expert_encoder_from_nemo
                14      STORE_FAST                      3: load_parallel_expert_encoder_from_nemo
                16      POP_TOP                         
                18      PUSH_NULL                       
                20      LOAD_FAST                       2: is_parallel_expert_encoder_nemo
                22      LOAD_FAST                       1: pe_encoder_path
                24      CALL                            1
                32      POP_JUMP_IF_TRUE                15 (to 64)
                34      LOAD_GLOBAL                     7: NULL + ValueError
                44      LOAD_CONST                      3: 'pe_encoder_path='
                46      LOAD_FAST                       1: pe_encoder_path
                48      FORMAT_VALUE                    2 (FVC_REPR)
                50      LOAD_CONST                      4: ' is not a ParallelExpertEncoderPT .nemo bundle.'
                52      BUILD_STRING                    3
                54      CALL                            1
                62      RAISE_VARARGS                   1
                64      PUSH_NULL                       
                66      LOAD_FAST                       3: load_parallel_expert_encoder_from_nemo
                68      LOAD_FAST                       1: pe_encoder_path
                70      LOAD_CONST                      5: 'cpu'
                72      LOAD_CONST                      6: True
                74      KW_NAMES                        7: ('map_location', 'strict')
                76      CALL                            3
                84      STORE_FAST                      4: pe_encoder
                86      LOAD_GLOBAL                     9: NULL + getattr
                96      LOAD_FAST                       0: perception
                98      LOAD_CONST                      8: 'encoder'
                100     LOAD_CONST                      9: None
                102     CALL                            3
                110     STORE_FAST                      5: existing_encoder
                112     LOAD_FAST                       5: existing_encoder
                114     POP_JUMP_IF_NOT_NONE            11 (to 138)
                116     LOAD_GLOBAL                     11: NULL + RuntimeError
                126     LOAD_CONST                      10: 'perception module has no `encoder` attribute to replace with the PE bundle.'
                128     CALL                            1
                136     RAISE_VARARGS                   1
                138     LOAD_GLOBAL                     13: NULL + int
                148     LOAD_GLOBAL                     9: NULL + getattr
                158     LOAD_FAST                       5: existing_encoder
                160     LOAD_CONST                      11: 'd_model'
                162     LOAD_CONST                      12: -1
                164     CALL                            3
                172     CALL                            1
                180     STORE_FAST                      6: existing_d_model
                182     LOAD_FAST                       6: existing_d_model
                184     LOAD_CONST                      1: 0
                186     COMPARE_OP                      68 (>)
                190     POP_JUMP_IF_FALSE               52 (to 296)
                192     LOAD_GLOBAL                     13: NULL + int
                202     LOAD_FAST                       4: pe_encoder
                204     LOAD_ATTR                       14: d_model
                224     CALL                            1
                232     LOAD_FAST                       6: existing_d_model
                234     COMPARE_OP                      55 (!=)
                238     POP_JUMP_IF_FALSE               28 (to 296)
                240     LOAD_GLOBAL                     7: NULL + ValueError
                250     LOAD_CONST                      13: 'ParallelExpertEncoder d_model='
                252     LOAD_FAST                       4: pe_encoder
                254     LOAD_ATTR                       14: d_model
                274     FORMAT_VALUE                    0 (FVC_NONE)
                276     LOAD_CONST                      14: ' does not match the existing perception encoder d_model='
                278     LOAD_FAST                       6: existing_d_model
                280     FORMAT_VALUE                    0 (FVC_NONE)
                282     LOAD_CONST                      15: '.'
                284     BUILD_STRING                    5
                286     CALL                            1
                294     RAISE_VARARGS                   1
                296     NOP                             
                298     LOAD_CONST                      9: None
                300     LOAD_FAST                       0: perception
                302     LOAD_ATTR                       16: preprocessor
                322     LOAD_ATTR                       18: featurizer
                342     STORE_ATTR                      10: normalize
                352     LOAD_FAST                       4: pe_encoder
                354     LOAD_FAST                       0: perception
                356     STORE_ATTR                      12: encoder
                366     RETURN_CONST                    9: None
                368     PUSH_EXC_INFO                   
                370     LOAD_GLOBAL                     22: AttributeError
                380     CHECK_EXC_MATCH                 
                382     POP_JUMP_IF_FALSE               10 (to 404)
                384     POP_TOP                         
                386     POP_EXCEPT                      
                388     LOAD_FAST                       4: pe_encoder
                390     LOAD_FAST                       0: perception
                392     STORE_ATTR                      12: encoder
                402     RETURN_CONST                    9: None
                404     RERAISE                         0
                406     COPY                            3
                408     POP_EXCEPT                      
                410     RERAISE                         1
            [Exception Table]
                298 to 352 -> 368 [0] 
                368 to 386 -> 406 [1] lasti
                404 to 406 -> 406 [1] lasti
        'perception_cfg'
        'output_dim'
        [Code]
            File Name: /code/NeMo/nemo/collections/speechlm2/vllm/nemotron_v3/model.py
            Object Name: _load_nemo_perception
            Qualified Name: _load_nemo_perception
            Arg Count: 3
            Pos Only Arg Count: 0
            KW Only Arg Count: 0
            Stack Size: 5
            Flags: 0x00000003 (CO_OPTIMIZED | CO_NEWLOCALS)
            [Names]
                'omegaconf'
                'DictConfig'
                'nemo.collections.speechlm2.modules'
                'AudioPerceptionModule'
                'ImportError'
                'output_dim'
                '_mount_parallel_expert_encoder'
                'nemo.collections.asr.modules.conformer_encoder'
                'ConformerEncoder'
                'modules'
                'isinstance'
                'sync_max_audio_length'
                'Exception'
                'eval'
            [Locals+Names]
                'perception_cfg'
                'output_dim'
                'pe_encoder_path'
                'DictConfig'
                'AudioPerceptionModule'
                'e'
                'cfg'
                'perception'
                'ConformerEncoder'
                'module'
            [Constants]
                None
                0
                (
                    'DictConfig'
                )
                (
                    'AudioPerceptionModule'
                )
                'NeMo is required for the audio encoder. Install with: pip install nemo_toolkit[asr]'
                'output_dim'
                (
                    'ConformerEncoder'
                )
                False
            [Disassembly]
                0       RESUME                          0
                2       NOP                             
                4       LOAD_CONST                      1: 0
                6       LOAD_CONST                      2: ('DictConfig',)
                8       IMPORT_NAME                     0: omegaconf
                10      IMPORT_FROM                     1: DictConfig
                12      STORE_FAST                      3: DictConfig
                14      POP_TOP                         
                16      LOAD_CONST                      1: 0
                18      LOAD_CONST                      3: ('AudioPerceptionModule',)
                20      IMPORT_NAME                     2: nemo.collections.speechlm2.modules
                22      IMPORT_FROM                     3: AudioPerceptionModule
                24      STORE_FAST                      4: AudioPerceptionModule
                26      POP_TOP                         
                28      PUSH_NULL                       
                30      LOAD_FAST                       3: DictConfig
                32      LOAD_FAST                       0: perception_cfg
                34      CALL                            1
                42      STORE_FAST                      6: cfg
                44      LOAD_CONST                      5: 'output_dim'
                46      LOAD_FAST                       6: cfg
                48      CONTAINS_OP                     1 (not in)
                50      POP_JUMP_IF_FALSE               7 (to 66)
                52      LOAD_FAST                       1: output_dim
                54      LOAD_FAST                       6: cfg
                56      STORE_ATTR                      5: output_dim
                66      PUSH_NULL                       
                68      LOAD_FAST                       4: AudioPerceptionModule
                70      LOAD_FAST                       6: cfg
                72      CALL                            1
                80      STORE_FAST                      7: perception
                82      LOAD_FAST                       2: pe_encoder_path
                84      POP_JUMP_IF_FALSE               12 (to 110)
                86      LOAD_GLOBAL                     13: NULL + _mount_parallel_expert_encoder
                96      LOAD_FAST                       7: perception
                98      LOAD_FAST                       2: pe_encoder_path
                100     CALL                            2
                108     POP_TOP                         
                110     NOP                             
                112     LOAD_CONST                      1: 0
                114     LOAD_CONST                      6: ('ConformerEncoder',)
                116     IMPORT_NAME                     7: nemo.collections.asr.modules.conformer_encoder
                118     IMPORT_FROM                     8: ConformerEncoder
                120     STORE_FAST                      8: ConformerEncoder
                122     POP_TOP                         
                124     LOAD_FAST                       7: perception
                126     LOAD_ATTR                       19: modules
                146     CALL                            0
                154     GET_ITER                        
                156     FOR_ITER                        22 (to 202)
                160     STORE_FAST                      9: module
                162     LOAD_GLOBAL                     21: NULL + isinstance
                172     LOAD_FAST                       9: module
                174     LOAD_FAST                       8: ConformerEncoder
                176     CALL                            2
                184     POP_JUMP_IF_TRUE                1 (to 188)
                186     JUMP_BACKWARD                   16 (to 156)
                188     LOAD_CONST                      7: False
                190     LOAD_FAST                       9: module
                192     STORE_ATTR                      11: sync_max_audio_length
                202     JUMP_BACKWARD                   24 (to 156)
                204     END_FOR                         
                206     NOP                             
                208     LOAD_FAST                       7: perception
                210     LOAD_ATTR                       27: eval
                230     CALL                            0
                238     POP_TOP                         
                240     LOAD_FAST                       7: perception
                242     RETURN_VALUE                    
                244     PUSH_EXC_INFO                   
                246     LOAD_GLOBAL                     8: ImportError
                256     CHECK_EXC_MATCH                 
                258     POP_JUMP_IF_FALSE               17 (to 294)
                260     STORE_FAST                      5: e
                262     LOAD_GLOBAL                     9: NULL + ImportError
                272     LOAD_CONST                      4: 'NeMo is required for the audio encoder. Install with: pip install nemo_toolkit[asr]'
                274     CALL                            1
                282     LOAD_FAST                       5: e
                284     RAISE_VARARGS                   2
                286     LOAD_CONST                      0: None
                288     STORE_FAST                      5: e
                290     DELETE_FAST                     5: e
                292     RERAISE                         1
                294     RERAISE                         0
                296     COPY                            3
                298     POP_EXCEPT                      
                300     RERAISE                         1
                302     PUSH_EXC_INFO                   
                304     LOAD_GLOBAL                     24: Exception
                314     CHECK_EXC_MATCH                 
                316     POP_JUMP_IF_FALSE               3 (to 324)
                318     POP_TOP                         
                320     POP_EXCEPT                      
                322     JUMP_BACKWARD                   58 (to 208)
                324     RERAISE                         0
                326     COPY                            3
                328     POP_EXCEPT                      
                330     RERAISE                         1
            [Exception Table]
                4 to 28 -> 244 [0] 
                112 to 186 -> 302 [0] 
                188 to 206 -> 302 [0] 
                244 to 262 -> 296 [1] lasti
                262 to 286 -> 286 [1] lasti
                286 to 296 -> 296 [1] lasti
                302 to 320 -> 326 [1] lasti
                324 to 326 -> 326 [1] lasti
        [Code]
            File Name: /code/NeMo/nemo/collections/speechlm2/vllm/nemotron_v3/model.py
            Object Name: NeMoSpeechLMAudioInputs
            Qualified Name: NeMoSpeechLMAudioInputs
            Arg Count: 0
            Pos Only Arg Count: 0
            KW Only Arg Count: 0
            Stack Size: 6
            Flags: 0x00000000
            [Names]
                '__name__'
                '__module__'
                '__qualname__'
                '__doc__'
                'type'
                'Literal'
                '__annotations__'
                'Annotated'
                'torch'
                'Tensor'
                'list'
                'TensorShape'
            [Locals+Names]
            [Constants]
                'NeMoSpeechLMAudioInputs'
                "Typed schema for audio inputs passed through vLLM's multimodal pipeline."
                'audio_features'
                'type'
                'b'
                't'
                'audio_signal'
                'audio_signal_length'
                None
            [Disassembly]
                0       RESUME                          0
                2       LOAD_NAME                       0: __name__
                4       STORE_NAME                      1: __module__
                6       LOAD_CONST                      0: 'NeMoSpeechLMAudioInputs'
                8       STORE_NAME                      2: __qualname__
                10      SETUP_ANNOTATIONS               
                12      LOAD_CONST                      1: "Typed schema for audio inputs passed through vLLM's multimodal pipeline."
                14      STORE_NAME                      3: __doc__
                16      LOAD_CONST                      2: 'audio_features'
                18      STORE_NAME                      4: type
                20      LOAD_NAME                       5: Literal
                22      LOAD_CONST                      2: 'audio_features'
                24      BINARY_SUBSCR                   
                28      LOAD_NAME                       6: __annotations__
                30      LOAD_CONST                      3: 'type'
                32      STORE_SUBSCR                    
                36      LOAD_NAME                       7: Annotated
                38      LOAD_NAME                       8: torch
                40      LOAD_ATTR                       18: Tensor
                60      LOAD_NAME                       10: list
                62      LOAD_NAME                       8: torch
                64      LOAD_ATTR                       18: Tensor
                84      BINARY_SUBSCR                   
                88      BINARY_OP                       7 (|)
                92      PUSH_NULL                       
                94      LOAD_NAME                       11: TensorShape
                96      LOAD_CONST                      4: 'b'
                98      LOAD_CONST                      5: 't'
                100     CALL                            2
                108     BUILD_TUPLE                     2
                110     BINARY_SUBSCR                   
                114     LOAD_NAME                       6: __annotations__
                116     LOAD_CONST                      6: 'audio_signal'
                118     STORE_SUBSCR                    
                122     LOAD_NAME                       7: Annotated
                124     LOAD_NAME                       8: torch
                126     LOAD_ATTR                       18: Tensor
                146     PUSH_NULL                       
                148     LOAD_NAME                       11: TensorShape
                150     LOAD_CONST                      4: 'b'
                152     CALL                            1
                160     BUILD_TUPLE                     2
                162     BINARY_SUBSCR                   
                166     LOAD_NAME                       6: __annotations__
                168     LOAD_CONST                      7: 'audio_signal_length'
                170     STORE_SUBSCR                    
                174     RETURN_CONST                    8: None
            [Exception Table]
        'NeMoSpeechLMAudioInputs'
        [Code]
            File Name: /code/NeMo/nemo/collections/speechlm2/vllm/nemotron_v3/model.py
            Object Name: NeMoSpeechLMProcessingInfo
            Qualified Name: NeMoSpeechLMProcessingInfo
            Arg Count: 0
            Pos Only Arg Count: 0
            KW Only Arg Count: 0
            Stack Size: 5
            Flags: 0x00000000
            [Names]
                '__name__'
                '__module__'
                '__qualname__'
                '__doc__'
                'MultiModalDataParser'
                'get_data_parser'
                'Mapping'
                'str'
                'int'
                'get_supported_mm_limits'
                'get_max_audio_tokens'
                'get_max_audio_len'
                'staticmethod'
                '_estimate_audio_tokens'
            [Locals+Names]
            [Constants]
                'NeMoSpeechLMProcessingInfo'
                'Processing info for NeMo Speech LM: audio token estimation and limits.'
                'return'
                [Code]
                    File Name: /code/NeMo/nemo/collections/speechlm2/vllm/nemotron_v3/model.py
                    Object Name: get_data_parser
                    Qualified Name: NeMoSpeechLMProcessingInfo.get_data_parser
                    Arg Count: 1
                    Pos Only Arg Count: 0
                    KW Only Arg Count: 0
                    Stack Size: 5
                    Flags: 0x00000003 (CO_OPTIMIZED | CO_NEWLOCALS)
                    [Names]
                        'MultiModalDataParser'
                        '_SAMPLING_RATE'
                        '_get_expected_hidden_size'
                    [Locals+Names]
                        'self'
                    [Constants]
                        None
                        (
                            'target_sr'
                            'expected_hidden_size'
                        )
                    [Disassembly]
                        0       RESUME                          0
                        2       LOAD_GLOBAL                     1: NULL + MultiModalDataParser
                        12      LOAD_GLOBAL                     2: _SAMPLING_RATE
                        22      LOAD_FAST                       0: self
                        24      LOAD_ATTR                       5: _get_expected_hidden_size
                        44      CALL                            0
                        52      KW_NAMES                        1: ('target_sr', 'expected_hidden_size')
                        54      CALL                            2
                        62      RETURN_VALUE                    
                    [Exception Table]
                None
                [Code]
                    File Name: /code/NeMo/nemo/collections/speechlm2/vllm/nemotron_v3/model.py
                    Object Name: get_supported_mm_limits
                    Qualified Name: NeMoSpeechLMProcessingInfo.get_supported_mm_limits
                    Arg Count: 1
                    Pos Only Arg Count: 0
                    KW Only Arg Count: 0
                    Stack Size: 2
                    Flags: 0x00000003 (CO_OPTIMIZED | CO_NEWLOCALS)
                    [Names]
                    [Locals+Names]
                        'self'
                    [Constants]
                        None
                        'audio'
                        1
                    [Disassembly]
                        0       RESUME                          0
                        2       LOAD_CONST                      1: 'audio'
                        4       LOAD_CONST                      2: 1
                        6       BUILD_MAP                       1
                        8       RETURN_VALUE                    
                    [Exception Table]
                [Code]
                    File Name: /code/NeMo/nemo/collections/speechlm2/vllm/nemotron_v3/model.py
                    Object Name: get_max_audio_tokens
                    Qualified Name: NeMoSpeechLMProcessingInfo.get_max_audio_tokens
                    Arg Count: 1
                    Pos Only Arg Count: 0
                    KW Only Arg Count: 0
                    Stack Size: 4
                    Flags: 0x00000003 (CO_OPTIMIZED | CO_NEWLOCALS)
                    [Names]
                        '_estimate_audio_tokens'
                        'get_max_audio_len'
                    [Locals+Names]
                        'self'
                    [Constants]
                        None
                    [Disassembly]
                        0       RESUME                          0
                        2       LOAD_FAST                       0: self
                        4       LOAD_ATTR                       1: _estimate_audio_tokens
                        24      LOAD_FAST                       0: self
                        26      LOAD_ATTR                       3: get_max_audio_len
                        46      CALL                            0
                        54      CALL                            1
                        62      RETURN_VALUE                    
                    [Exception Table]
                [Code]
                    File Name: /code/NeMo/nemo/collections/speechlm2/vllm/nemotron_v3/model.py
                    Object Name: get_max_audio_len
                    Qualified Name: NeMoSpeechLMProcessingInfo.get_max_audio_len
                    Arg Count: 1
                    Pos Only Arg Count: 0
                    KW Only Arg Count: 0
                    Stack Size: 4
                    Flags: 0x00000003 (CO_OPTIMIZED | CO_NEWLOCALS)
                    [Names]
                        'int'
                        '_MAX_AUDIO_DURATION_S'
                        '_SAMPLING_RATE'
                    [Locals+Names]
                        'self'
                    [Constants]
                        None
                    [Disassembly]
                        0       RESUME                          0
                        2       LOAD_GLOBAL                     1: NULL + int
                        12      LOAD_GLOBAL                     2: _MAX_AUDIO_DURATION_S
                        22      LOAD_GLOBAL                     4: _SAMPLING_RATE
                        32      BINARY_OP                       5 (*)
                        36      CALL                            1
                        44      RETURN_VALUE                    
                    [Exception Table]
                'audio_length_samples'
                [Code]
                    File Name: /code/NeMo/nemo/collections/speechlm2/vllm/nemotron_v3/model.py
                    Object Name: _estimate_audio_tokens
                    Qualified Name: NeMoSpeechLMProcessingInfo._estimate_audio_tokens
                    Arg Count: 1
                    Pos Only Arg Count: 0
                    KW Only Arg Count: 0
                    Stack Size: 6
                    Flags: 0x00000003 (CO_OPTIMIZED | CO_NEWLOCALS)
                    [Names]
                        'float'
                        'range'
                        'max'
                        'int'
                    [Locals+Names]
                        'audio_length_samples'
                        'n_fft'
                        'hop_length'
                        'stft_pad'
                        'fbank_len'
                        'kernel'
                        'stride'
                        'repeat'
                        'add_pad'
                        'length'
                        '_'
                    [Constants]
                        None
                        512
                        160
                        2
                        (
                            3
                            2
                            3
                        )
                        1
                        1
                    [Disassembly]
                        0       RESUME                          0
                        2       LOAD_CONST                      1: 512
                        4       STORE_FAST                      1: n_fft
                        6       LOAD_CONST                      2: 160
                        8       STORE_FAST                      2: hop_length
                        10      LOAD_FAST                       1: n_fft
                        12      LOAD_CONST                      3: 2
                        14      BINARY_OP                       2 (//)
                        18      STORE_FAST                      3: stft_pad
                        20      LOAD_FAST                       0: audio_length_samples
                        22      LOAD_CONST                      3: 2
                        24      LOAD_FAST                       3: stft_pad
                        26      BINARY_OP                       5 (*)
                        30      BINARY_OP                       0 (+)
                        34      LOAD_FAST                       1: n_fft
                        36      BINARY_OP                       10 (-)
                        40      LOAD_FAST                       2: hop_length
                        42      BINARY_OP                       2 (//)
                        46      STORE_FAST                      4: fbank_len
                        48      LOAD_CONST                      4: (3, 2, 3)
                        50      UNPACK_SEQUENCE                 3
                        54      STORE_FAST                      5: kernel
                        56      STORE_FAST                      6: stride
                        58      STORE_FAST                      7: repeat
                        60      LOAD_CONST                      3: 2
                        62      LOAD_FAST                       5: kernel
                        64      BINARY_OP                       10 (-)
                        68      STORE_FAST                      8: add_pad
                        70      LOAD_GLOBAL                     1: NULL + float
                        80      LOAD_FAST                       4: fbank_len
                        82      CALL                            1
                        90      STORE_FAST                      9: length
                        92      LOAD_GLOBAL                     3: NULL + range
                        102     LOAD_FAST                       7: repeat
                        104     CALL                            1
                        112     GET_ITER                        
                        114     FOR_ITER                        13 (to 142)
                        118     STORE_FAST                      10: _
                        120     LOAD_FAST                       9: length
                        122     LOAD_FAST                       8: add_pad
                        124     BINARY_OP                       0 (+)
                        128     LOAD_FAST                       6: stride
                        130     BINARY_OP                       11 (/)
                        134     LOAD_CONST                      5: 1
                        136     BINARY_OP                       0 (+)
                        140     STORE_FAST                      9: length
                        142     JUMP_BACKWARD                   15 (to 114)
                        144     END_FOR                         
                        146     LOAD_GLOBAL                     5: NULL + max
                        156     LOAD_CONST                      6: 1
                        158     LOAD_GLOBAL                     7: NULL + int
                        168     LOAD_FAST                       9: length
                        170     CALL                            1
                        178     CALL                            2
                        186     RETURN_VALUE                    
                    [Exception Table]
            [Disassembly]
                0       RESUME                          0
                2       LOAD_NAME                       0: __name__
                4       STORE_NAME                      1: __module__
                6       LOAD_CONST                      0: 'NeMoSpeechLMProcessingInfo'
                8       STORE_NAME                      2: __qualname__
                10      LOAD_CONST                      1: 'Processing info for NeMo Speech LM: audio token estimation and limits.'
                12      STORE_NAME                      3: __doc__
                14      LOAD_CONST                      2: 'return'
                16      LOAD_NAME                       4: MultiModalDataParser
                18      BUILD_TUPLE                     2
                20      LOAD_CONST                      3: <CODE> get_data_parser
                22      MAKE_FUNCTION                   4
                24      STORE_NAME                      5: get_data_parser
                26      LOAD_CONST                      2: 'return'
                28      LOAD_NAME                       6: Mapping
                30      LOAD_NAME                       7: str
                32      LOAD_NAME                       8: int
                34      LOAD_CONST                      4: None
                36      BINARY_OP                       7 (|)
                40      BUILD_TUPLE                     2
                42      BINARY_SUBSCR                   
                46      BUILD_TUPLE                     2
                48      LOAD_CONST                      5: <CODE> get_supported_mm_limits
                50      MAKE_FUNCTION                   4
                52      STORE_NAME                      9: get_supported_mm_limits
                54      LOAD_CONST                      2: 'return'
                56      LOAD_NAME                       8: int
                58      BUILD_TUPLE                     2
                60      LOAD_CONST                      6: <CODE> get_max_audio_tokens
                62      MAKE_FUNCTION                   4
                64      STORE_NAME                      10: get_max_audio_tokens
                66      LOAD_CONST                      2: 'return'
                68      LOAD_NAME                       8: int
                70      BUILD_TUPLE                     2
                72      LOAD_CONST                      7: <CODE> get_max_audio_len
                74      MAKE_FUNCTION                   4
                76      STORE_NAME                      11: get_max_audio_len
                78      LOAD_NAME                       12: staticmethod
                80      LOAD_CONST                      8: 'audio_length_samples'
                82      LOAD_NAME                       8: int
                84      LOAD_CONST                      2: 'return'
                86      LOAD_NAME                       8: int
                88      BUILD_TUPLE                     4
                90      LOAD_CONST                      9: <CODE> _estimate_audio_tokens
                92      MAKE_FUNCTION                   4
                94      CALL                            0
                102     STORE_NAME                      13: _estimate_audio_tokens
                104     RETURN_CONST                    4: None
            [Exception Table]
        'NeMoSpeechLMProcessingInfo'
        [Code]
            File Name: /code/NeMo/nemo/collections/speechlm2/vllm/nemotron_v3/model.py
            Object Name: NeMoSpeechLMMultiModalProcessor
            Qualified Name: NeMoSpeechLMMultiModalProcessor
            Arg Count: 0
            Pos Only Arg Count: 0
            KW Only Arg Count: 0
            Stack Size: 10
            Flags: 0x00000000
            [Names]
                '__name__'
                '__module__'
                '__qualname__'
                '__doc__'
                'BatchFeature'
                'Mapping'
                'str'
                'object'
                'MultiModalFieldConfig'
                '_get_mm_fields_config'
                'MultiModalDataItems'
                'bool'
                '_hf_processor_applies_updates'
                'MultiModalKwargsItems'
                'list'
                'PromptUpdate'
                '_get_prompt_updates'
                '_call_hf_processor'
            [Locals+Names]
            [Constants]
                'NeMoSpeechLMMultiModalProcessor'
                'Multimodal processor that handles audio tokenization and prompt expansion.'
                'hf_inputs'
                'hf_processor_mm_kwargs'
                'return'
                [Code]
                    File Name: /code/NeMo/nemo/collections/speechlm2/vllm/nemotron_v3/model.py
                    Object Name: _get_mm_fields_config
                    Qualified Name: NeMoSpeechLMMultiModalProcessor._get_mm_fields_config
                    Arg Count: 3
                    Pos Only Arg Count: 0
                    KW Only Arg Count: 0
                    Stack Size: 6
                    Flags: 0x00000003 (CO_OPTIMIZED | CO_NEWLOCALS)
                    [Names]
                        'dict'
                        'MultiModalFieldConfig'
                        'batched'
                    [Locals+Names]
                        'self'
                        'hf_inputs'
                        'hf_processor_mm_kwargs'
                    [Constants]
                        None
                        'audio'
                        (
                            'audio_signal'
                            'audio_signal_length'
                        )
                    [Disassembly]
                        0       RESUME                          0
                        2       LOAD_GLOBAL                     1: NULL + dict
                        12      LOAD_GLOBAL                     3: NULL + MultiModalFieldConfig
                        22      LOAD_ATTR                       4: batched
                        42      LOAD_CONST                      1: 'audio'
                        44      CALL                            1
                        52      LOAD_GLOBAL                     3: NULL + MultiModalFieldConfig
                        62      LOAD_ATTR                       4: batched
                        82      LOAD_CONST                      1: 'audio'
                        84      CALL                            1
                        92      KW_NAMES                        2: ('audio_signal', 'audio_signal_length')
                        94      CALL                            2
                        102     RETURN_VALUE                    
                    [Exception Table]
                'prompt_text'
                'mm_items'
                'tokenization_kwargs'
                [Code]
                    File Name: /code/NeMo/nemo/collections/speechlm2/vllm/nemotron_v3/model.py
                    Object Name: _hf_processor_applies_updates
                    Qualified Name: NeMoSpeechLMMultiModalProcessor._hf_processor_applies_updates
                    Arg Count: 5
                    Pos Only Arg Count: 0
                    KW Only Arg Count: 0
                    Stack Size: 0
                    Flags: 0x00000003 (CO_OPTIMIZED | CO_NEWLOCALS)
                    [Names]
                    [Locals+Names]
                        'self'
                        'prompt_text'
                        'mm_items'
                        'hf_processor_mm_kwargs'
                        'tokenization_kwargs'
                    [Constants]
                        None
                        False
                    [Disassembly]
                        0       RESUME                          0
                        2       RETURN_CONST                    1: False
                    [Exception Table]
                'out_mm_kwargs'
                [Code]
                    File Name: /code/NeMo/nemo/collections/speechlm2/vllm/nemotron_v3/model.py
                    Object Name: _get_prompt_updates
                    Qualified Name: NeMoSpeechLMMultiModalProcessor._get_prompt_updates
                    Arg Count: 4
                    Pos Only Arg Count: 0
                    KW Only Arg Count: 0
                    Stack Size: 5
                    Flags: 0x00000003 (CO_OPTIMIZED | CO_NEWLOCALS)
                    [Names]
                        'int'
                        'PromptReplacement'
                        '_AUDIO_PLACEHOLDER'
                    [Locals+Names]
                        'self'
                        'mm_items'
                        'hf_processor_mm_kwargs'
                        'out_mm_kwargs'
                        'get_replacement'
                    [Constants]
                        None
                        'item_idx'
                        [Code]
                            File Name: /code/NeMo/nemo/collections/speechlm2/vllm/nemotron_v3/model.py
                            Object Name: get_replacement
                            Qualified Name: NeMoSpeechLMMultiModalProcessor._get_prompt_updates.<locals>.get_replacement
                            Arg Count: 1
                            Pos Only Arg Count: 0
                            KW Only Arg Count: 0
                            Stack Size: 4
                            Flags: 0x00000013 (CO_OPTIMIZED | CO_NEWLOCALS | CO_NESTED)
                            [Names]
                                'get_items'
                                'AudioProcessorItems'
                                'get'
                                'info'
                                '_estimate_audio_tokens'
                                'shape'
                                '_AUDIO_PLACEHOLDER'
                                'PromptUpdateDetails'
                                'select_text'
                            [Locals+Names]
                                'item_idx'
                                'audios'
                                'audio'
                                'n_tokens'
                                'repl_full'
                                'mm_items'
                                'self'
                            [Constants]
                                None
                                'audio'
                                -1
                            [Disassembly]
                                0       COPY_FREE_VARS                  2
                                2       RESUME                          0
                                4       LOAD_DEREF                      5: mm_items
                                6       LOAD_ATTR                       1: get_items
                                26      LOAD_CONST                      1: 'audio'
                                28      LOAD_GLOBAL                     2: AudioProcessorItems
                                38      CALL                            2
                                46      STORE_FAST                      1: audios
                                48      LOAD_FAST                       1: audios
                                50      LOAD_ATTR                       5: get
                                70      LOAD_FAST                       0: item_idx
                                72      CALL                            1
                                80      STORE_FAST                      2: audio
                                82      LOAD_DEREF                      6: self
                                84      LOAD_ATTR                       6: info
                                104     LOAD_ATTR                       9: _estimate_audio_tokens
                                124     LOAD_FAST                       2: audio
                                126     LOAD_ATTR                       10: shape
                                146     LOAD_CONST                      2: -1
                                148     BINARY_SUBSCR                   
                                152     CALL                            1
                                160     STORE_FAST                      3: n_tokens
                                162     LOAD_GLOBAL                     12: _AUDIO_PLACEHOLDER
                                172     LOAD_FAST                       3: n_tokens
                                174     BINARY_OP                       5 (*)
                                178     STORE_FAST                      4: repl_full
                                180     LOAD_GLOBAL                     15: NULL + PromptUpdateDetails
                                190     LOAD_ATTR                       16: select_text
                                210     LOAD_FAST                       4: repl_full
                                212     LOAD_GLOBAL                     12: _AUDIO_PLACEHOLDER
                                222     CALL                            2
                                230     RETURN_VALUE                    
                            [Exception Table]
                        'audio'
                        (
                            'modality'
                            'target'
                            'replacement'
                        )
                    [Disassembly]
                        0       MAKE_CELL                       0: self
                        2       MAKE_CELL                       1: mm_items
                        4       RESUME                          0
                        6       LOAD_CONST                      1: 'item_idx'
                        8       LOAD_GLOBAL                     0: int
                        18      BUILD_TUPLE                     2
                        20      LOAD_CLOSURE                    1: mm_items
                        22      LOAD_CLOSURE                    0: self
                        24      BUILD_TUPLE                     2
                        26      LOAD_CONST                      2: <CODE> get_replacement
                        28      MAKE_FUNCTION                   12
                        30      STORE_FAST                      4: get_replacement
                        32      LOAD_GLOBAL                     3: NULL + PromptReplacement
                        42      LOAD_CONST                      3: 'audio'
                        44      LOAD_GLOBAL                     4: _AUDIO_PLACEHOLDER
                        54      LOAD_FAST                       4: get_replacement
                        56      KW_NAMES                        4: ('modality', 'target', 'replacement')
                        58      CALL                            3
                        66      BUILD_LIST                      1
                        68      RETURN_VALUE                    
                    [Exception Table]
                'prompt'
                'mm_data'
                'mm_kwargs'
                'tok_kwargs'
                [Code]
                    File Name: /code/NeMo/nemo/collections/speechlm2/vllm/nemotron_v3/model.py
                    Object Name: _call_hf_processor
                    Qualified Name: NeMoSpeechLMMultiModalProcessor._call_hf_processor
                    Arg Count: 5
                    Pos Only Arg Count: 0
                    KW Only Arg Count: 0
                    Stack Size: 6
                    Flags: 0x00000003 (CO_OPTIMIZED | CO_NEWLOCALS)
                    [Names]
                        'info'
                        'get_tokenizer'
                        '_ensure_special_tokens'
                        'dict'
                        'pop'
                        're'
                        'split'
                        'escape'
                        '_AUDIO_PLACEHOLDER'
                        'enumerate'
                        'len'
                        'isinstance'
                        'torch'
                        'Tensor'
                        'as_tensor'
                        'float32'
                        'dim'
                        'squeeze'
                        '_estimate_audio_tokens'
                        'shape'
                        'append'
                        'join'
                        'encode'
                        'BatchFeature'
                        'tensor'
                    [Locals+Names]
                        'self'
                        'prompt'
                        'mm_data'
                        'mm_kwargs'
                        'tok_kwargs'
                        'tokenizer'
                        'audios'
                        'audio_list'
                        'audio_lengths'
                        'parts'
                        'audio_idx'
                        'i'
                        'part'
                        'audio'
                        'audio_tensor'
                        'n_tokens'
                        'prompt_ids'
                        'result'
                    [Constants]
                        None
                        'audios'
                        '('
                        ')'
                        0
                        (
                            'dtype'
                        )
                        1
                        -1
                        ''
                        True
                        (
                            'add_special_tokens'
                        )
                        (
                            'input_ids'
                        )
                        'pt'
                        (
                            'tensor_type'
                        )
                        'audio_signal'
                        'audio_signal_length'
                    [Disassembly]
                        0       RESUME                          0
                        2       LOAD_FAST                       0: self
                        4       LOAD_ATTR                       0: info
                        24      LOAD_ATTR                       3: get_tokenizer
                        44      CALL                            0
                        52      STORE_FAST                      5: tokenizer
                        54      LOAD_GLOBAL                     5: NULL + _ensure_special_tokens
                        64      LOAD_FAST                       5: tokenizer
                        66      CALL                            1
                        74      POP_TOP                         
                        76      LOAD_GLOBAL                     7: NULL + dict
                        86      LOAD_FAST                       2: mm_data
                        88      CALL                            1
                        96      STORE_FAST                      2: mm_data
                        98      LOAD_FAST                       2: mm_data
                        100     LOAD_ATTR                       9: pop
                        120     LOAD_CONST                      1: 'audios'
                        122     BUILD_LIST                      0
                        124     CALL                            2
                        132     STORE_FAST                      6: audios
                        134     LOAD_FAST                       6: audios
                        136     POP_JUMP_IF_FALSE               325 (to 790)
                        140     BUILD_LIST                      0
                        142     STORE_FAST                      7: audio_list
                        144     BUILD_LIST                      0
                        146     STORE_FAST                      8: audio_lengths
                        148     LOAD_GLOBAL                     11: NULL + re
                        158     LOAD_ATTR                       12: split
                        178     LOAD_CONST                      2: '('
                        180     LOAD_GLOBAL                     11: NULL + re
                        190     LOAD_ATTR                       14: escape
                        210     LOAD_GLOBAL                     16: _AUDIO_PLACEHOLDER
                        220     CALL                            1
                        228     FORMAT_VALUE                    0 (FVC_NONE)
                        230     LOAD_CONST                      3: ')'
                        232     BUILD_STRING                    3
                        234     LOAD_FAST                       1: prompt
                        236     CALL                            2
                        244     STORE_FAST                      9: parts
                        246     LOAD_CONST                      4: 0
                        248     STORE_FAST                      10: audio_idx
                        250     LOAD_GLOBAL                     19: NULL + enumerate
                        260     LOAD_FAST                       9: parts
                        262     CALL                            1
                        270     GET_ITER                        
                        272     FOR_ITER                        239 (to 752)
                        276     UNPACK_SEQUENCE                 2
                        280     STORE_FAST                      11: i
                        282     STORE_FAST                      12: part
                        284     LOAD_FAST                       12: part
                        286     LOAD_GLOBAL                     16: _AUDIO_PLACEHOLDER
                        296     COMPARE_OP                      40 (==)
                        300     POP_JUMP_IF_TRUE                1 (to 304)
                        302     JUMP_BACKWARD                   16 (to 272)
                        304     LOAD_FAST                       10: audio_idx
                        306     LOAD_GLOBAL                     21: NULL + len
                        316     LOAD_FAST                       6: audios
                        318     CALL                            1
                        326     COMPARE_OP                      2 (<)
                        330     POP_JUMP_IF_TRUE                1 (to 334)
                        332     JUMP_BACKWARD                   31 (to 272)
                        334     LOAD_FAST                       6: audios
                        336     LOAD_FAST                       10: audio_idx
                        338     BINARY_SUBSCR                   
                        342     STORE_FAST                      13: audio
                        344     LOAD_GLOBAL                     23: NULL + isinstance
                        354     LOAD_FAST                       13: audio
                        356     LOAD_GLOBAL                     24: torch
                        366     LOAD_ATTR                       26: Tensor
                        386     CALL                            2
                        394     POP_JUMP_IF_FALSE               2 (to 400)
                        396     LOAD_FAST                       13: audio
                        398     JUMP_FORWARD                    36 (to 472)
                        400     LOAD_GLOBAL                     25: NULL + torch
                        410     LOAD_ATTR                       28: as_tensor
                        430     LOAD_FAST                       13: audio
                        432     LOAD_GLOBAL                     24: torch
                        442     LOAD_ATTR                       30: float32
                        462     KW_NAMES                        5: ('dtype',)
                        464     CALL                            2
                        472     STORE_FAST                      14: audio_tensor
                        474     LOAD_FAST                       14: audio_tensor
                        476     LOAD_ATTR                       33: dim
                        496     CALL                            0
                        504     LOAD_CONST                      6: 1
                        506     COMPARE_OP                      68 (>)
                        510     POP_JUMP_IF_FALSE               16 (to 544)
                        512     LOAD_FAST                       14: audio_tensor
                        514     LOAD_ATTR                       35: squeeze
                        534     CALL                            0
                        542     STORE_FAST                      14: audio_tensor
                        544     LOAD_FAST                       0: self
                        546     LOAD_ATTR                       0: info
                        566     LOAD_ATTR                       37: _estimate_audio_tokens
                        586     LOAD_FAST                       14: audio_tensor
                        588     LOAD_ATTR                       38: shape
                        608     LOAD_CONST                      7: -1
                        610     BINARY_SUBSCR                   
                        614     CALL                            1
                        622     STORE_FAST                      15: n_tokens
                        624     LOAD_GLOBAL                     16: _AUDIO_PLACEHOLDER
                        634     LOAD_FAST                       15: n_tokens
                        636     BINARY_OP                       5 (*)
                        640     LOAD_FAST                       9: parts
                        642     LOAD_FAST                       11: i
                        644     STORE_SUBSCR                    
                        648     LOAD_FAST                       7: audio_list
                        650     LOAD_ATTR                       41: append
                        670     LOAD_FAST                       14: audio_tensor
                        672     CALL                            1
                        680     POP_TOP                         
                        682     LOAD_FAST                       8: audio_lengths
                        684     LOAD_ATTR                       41: append
                        704     LOAD_FAST                       14: audio_tensor
                        706     LOAD_ATTR                       38: shape
                        726     LOAD_CONST                      7: -1
                        728     BINARY_SUBSCR                   
                        732     CALL                            1
                        740     POP_TOP                         
                        742     LOAD_FAST                       10: audio_idx
                        744     LOAD_CONST                      6: 1
                        746     BINARY_OP                       13 (+=)
                        750     STORE_FAST                      10: audio_idx
                        752     JUMP_BACKWARD                   241 (to 272)
                        754     END_FOR                         
                        756     LOAD_CONST                      8: ''
                        758     LOAD_ATTR                       43: join
                        778     LOAD_FAST                       9: parts
                        780     CALL                            1
                        788     STORE_FAST                      1: prompt
                        790     LOAD_FAST                       5: tokenizer
                        792     LOAD_ATTR                       45: encode
                        812     LOAD_FAST                       1: prompt
                        814     LOAD_CONST                      9: True
                        816     KW_NAMES                        10: ('add_special_tokens',)
                        818     CALL                            2
                        826     STORE_FAST                      16: prompt_ids
                        828     LOAD_GLOBAL                     47: NULL + BatchFeature
                        838     LOAD_GLOBAL                     7: NULL + dict
                        848     LOAD_FAST                       16: prompt_ids
                        850     BUILD_LIST                      1
                        852     KW_NAMES                        11: ('input_ids',)
                        854     CALL                            1
                        862     LOAD_CONST                      12: 'pt'
                        864     KW_NAMES                        13: ('tensor_type',)
                        866     CALL                            2
                        874     STORE_FAST                      17: result
                        876     LOAD_FAST                       6: audios
                        878     POP_JUMP_IF_FALSE               29 (to 938)
                        880     LOAD_FAST_CHECK                 7: audio_list
                        882     LOAD_FAST                       17: result
                        884     LOAD_CONST                      14: 'audio_signal'
                        886     STORE_SUBSCR                    
                        890     LOAD_GLOBAL                     25: NULL + torch
                        900     LOAD_ATTR                       48: tensor
                        920     LOAD_FAST_CHECK                 8: audio_lengths
                        922     CALL                            1
                        930     LOAD_FAST                       17: result
                        932     LOAD_CONST                      15: 'audio_signal_length'
                        934     STORE_SUBSCR                    
                        938     LOAD_FAST                       17: result
                        940     RETURN_VALUE                    
                    [Exception Table]
                None
            [Disassembly]
                0       RESUME                          0
                2       LOAD_NAME                       0: __name__
                4       STORE_NAME                      1: __module__
                6       LOAD_CONST                      0: 'NeMoSpeechLMMultiModalProcessor'
                8       STORE_NAME                      2: __qualname__
                10      LOAD_CONST                      1: 'Multimodal processor that handles audio tokenization and prompt expansion.'
                12      STORE_NAME                      3: __doc__
                14      LOAD_CONST                      2: 'hf_inputs'
                16      LOAD_NAME                       4: BatchFeature
                18      LOAD_CONST                      3: 'hf_processor_mm_kwargs'
                20      LOAD_NAME                       5: Mapping
                22      LOAD_NAME                       6: str
                24      LOAD_NAME                       7: object
                26      BUILD_TUPLE                     2
                28      BINARY_SUBSCR                   
                32      LOAD_CONST                      4: 'return'
                34      LOAD_NAME                       5: Mapping
                36      LOAD_NAME                       6: str
                38      LOAD_NAME                       8: MultiModalFieldConfig
                40      BUILD_TUPLE                     2
                42      BINARY_SUBSCR                   
                46      BUILD_TUPLE                     6
                48      LOAD_CONST                      5: <CODE> _get_mm_fields_config
                50      MAKE_FUNCTION                   4
                52      STORE_NAME                      9: _get_mm_fields_config
                54      LOAD_CONST                      6: 'prompt_text'
                56      LOAD_NAME                       6: str
                58      LOAD_CONST                      7: 'mm_items'
                60      LOAD_NAME                       10: MultiModalDataItems
                62      LOAD_CONST                      3: 'hf_processor_mm_kwargs'
                64      LOAD_NAME                       5: Mapping
                66      LOAD_NAME                       6: str
                68      LOAD_NAME                       7: object
                70      BUILD_TUPLE                     2
                72      BINARY_SUBSCR                   
                76      LOAD_CONST                      8: 'tokenization_kwargs'
                78      LOAD_NAME                       5: Mapping
                80      LOAD_NAME                       6: str
                82      LOAD_NAME                       7: object
                84      BUILD_TUPLE                     2
                86      BINARY_SUBSCR                   
                90      LOAD_CONST                      4: 'return'
                92      LOAD_NAME                       11: bool
                94      BUILD_TUPLE                     10
                96      LOAD_CONST                      9: <CODE> _hf_processor_applies_updates
                98      MAKE_FUNCTION                   4
                100     STORE_NAME                      12: _hf_processor_applies_updates
                102     LOAD_CONST                      7: 'mm_items'
                104     LOAD_NAME                       10: MultiModalDataItems
                106     LOAD_CONST                      3: 'hf_processor_mm_kwargs'
                108     LOAD_NAME                       5: Mapping
                110     LOAD_NAME                       6: str
                112     LOAD_NAME                       7: object
                114     BUILD_TUPLE                     2
                116     BINARY_SUBSCR                   
                120     LOAD_CONST                      10: 'out_mm_kwargs'
                122     LOAD_NAME                       13: MultiModalKwargsItems
                124     LOAD_CONST                      4: 'return'
                126     LOAD_NAME                       14: list
                128     LOAD_NAME                       15: PromptUpdate
                130     BINARY_SUBSCR                   
                134     BUILD_TUPLE                     8
                136     LOAD_CONST                      11: <CODE> _get_prompt_updates
                138     MAKE_FUNCTION                   4
                140     STORE_NAME                      16: _get_prompt_updates
                142     LOAD_CONST                      12: 'prompt'
                144     LOAD_NAME                       6: str
                146     LOAD_CONST                      13: 'mm_data'
                148     LOAD_NAME                       5: Mapping
                150     LOAD_NAME                       6: str
                152     LOAD_NAME                       7: object
                154     BUILD_TUPLE                     2
                156     BINARY_SUBSCR                   
                160     LOAD_CONST                      14: 'mm_kwargs'
                162     LOAD_NAME                       5: Mapping
                164     LOAD_NAME                       6: str
                166     LOAD_NAME                       7: object
                168     BUILD_TUPLE                     2
                170     BINARY_SUBSCR                   
                174     LOAD_CONST                      15: 'tok_kwargs'
                176     LOAD_NAME                       5: Mapping
                178     LOAD_NAME                       6: str
                180     LOAD_NAME                       7: object
                182     BUILD_TUPLE                     2
                184     BINARY_SUBSCR                   
                188     LOAD_CONST                      4: 'return'
                190     LOAD_NAME                       4: BatchFeature
                192     BUILD_TUPLE                     10
                194     LOAD_CONST                      16: <CODE> _call_hf_processor
                196     MAKE_FUNCTION                   4
                198     STORE_NAME                      17: _call_hf_processor
                200     RETURN_CONST                    17: None
            [Exception Table]
        'NeMoSpeechLMMultiModalProcessor'
        [Code]
            File Name: /code/NeMo/nemo/collections/speechlm2/vllm/nemotron_v3/model.py
            Object Name: NeMoSpeechLMDummyInputsBuilder
            Qualified Name: NeMoSpeechLMDummyInputsBuilder
            Arg Count: 0
            Pos Only Arg Count: 0
            KW Only Arg Count: 0
            Stack Size: 8
            Flags: 0x00000000
            [Names]
                '__name__'
                '__module__'
                '__qualname__'
                '__doc__'
                'int'
                'Mapping'
                'str'
                'BaseDummyOptions'
                'MultiModalDataDict'
                'get_dummy_mm_data'
                'get_dummy_text'
            [Locals+Names]
            [Constants]
                'NeMoSpeechLMDummyInputsBuilder'
                "Builds dummy audio inputs for vLLM's model profiling and warmup."
                'seq_len'
                'mm_counts'
                'mm_options'
                'return'
                [Code]
                    File Name: /code/NeMo/nemo/collections/speechlm2/vllm/nemotron_v3/model.py
                    Object Name: get_dummy_mm_data
                    Qualified Name: NeMoSpeechLMDummyInputsBuilder.get_dummy_mm_data
                    Arg Count: 4
                    Pos Only Arg Count: 0
                    KW Only Arg Count: 0
                    Stack Size: 5
                    Flags: 0x00000003 (CO_OPTIMIZED | CO_NEWLOCALS)
                    [Names]
                        'get'
                        '_get_dummy_audios'
                        'info'
                        'get_max_audio_len'
                    [Locals+Names]
                        'self'
                        'seq_len'
                        'mm_counts'
                        'mm_options'
                        'num_audios'
                    [Constants]
                        None
                        'audio'
                        0
                        (
                            'length'
                            'num_audios'
                        )
                    [Disassembly]
                        0       RESUME                          0
                        2       LOAD_FAST                       2: mm_counts
                        4       LOAD_ATTR                       1: get
                        24      LOAD_CONST                      1: 'audio'
                        26      LOAD_CONST                      2: 0
                        28      CALL                            2
                        36      STORE_FAST                      4: num_audios
                        38      LOAD_CONST                      1: 'audio'
                        40      LOAD_FAST                       0: self
                        42      LOAD_ATTR                       3: _get_dummy_audios
                        62      LOAD_FAST                       0: self
                        64      LOAD_ATTR                       4: info
                        84      LOAD_ATTR                       7: get_max_audio_len
                        104     CALL                            0
                        112     LOAD_FAST                       4: num_audios
                        114     KW_NAMES                        3: ('length', 'num_audios')
                        116     CALL                            2
                        124     BUILD_MAP                       1
                        126     RETURN_VALUE                    
                    [Exception Table]
                [Code]
                    File Name: /code/NeMo/nemo/collections/speechlm2/vllm/nemotron_v3/model.py
                    Object Name: get_dummy_text
                    Qualified Name: NeMoSpeechLMDummyInputsBuilder.get_dummy_text
                    Arg Count: 2
                    Pos Only Arg Count: 0
                    KW Only Arg Count: 0
                    Stack Size: 4
                    Flags: 0x00000003 (CO_OPTIMIZED | CO_NEWLOCALS)
                    [Names]
                        'get'
                        '_AUDIO_PLACEHOLDER'
                    [Locals+Names]
                        'self'
                        'mm_counts'
                        'num_audios'
                    [Constants]
                        None
                        'audio'
                        0
                        'Transcribe the following: '
                    [Disassembly]
                        0       RESUME                          0
                        2       LOAD_FAST                       1: mm_counts
                        4       LOAD_ATTR                       1: get
                        24      LOAD_CONST                      1: 'audio'
                        26      LOAD_CONST                      2: 0
                        28      CALL                            2
                        36      STORE_FAST                      2: num_audios
                        38      LOAD_CONST                      3: 'Transcribe the following: '
                        40      LOAD_GLOBAL                     2: _AUDIO_PLACEHOLDER
                        50      LOAD_FAST                       2: num_audios
                        52      BINARY_OP                       5 (*)
                        56      BINARY_OP                       0 (+)
                        60      RETURN_VALUE                    
                    [Exception Table]
                None
            [Disassembly]
                0       RESUME                          0
                2       LOAD_NAME                       0: __name__
                4       STORE_NAME                      1: __module__
                6       LOAD_CONST                      0: 'NeMoSpeechLMDummyInputsBuilder'
                8       STORE_NAME                      2: __qualname__
                10      LOAD_CONST                      1: "Builds dummy audio inputs for vLLM's model profiling and warmup."
                12      STORE_NAME                      3: __doc__
                14      LOAD_CONST                      2: 'seq_len'
                16      LOAD_NAME                       4: int
                18      LOAD_CONST                      3: 'mm_counts'
                20      LOAD_NAME                       5: Mapping
                22      LOAD_NAME                       6: str
                24      LOAD_NAME                       4: int
                26      BUILD_TUPLE                     2
                28      BINARY_SUBSCR                   
                32      LOAD_CONST                      4: 'mm_options'
                34      LOAD_NAME                       5: Mapping
                36      LOAD_NAME                       6: str
                38      LOAD_NAME                       7: BaseDummyOptions
                40      BUILD_TUPLE                     2
                42      BINARY_SUBSCR                   
                46      LOAD_CONST                      5: 'return'
                48      LOAD_NAME                       8: MultiModalDataDict
                50      BUILD_TUPLE                     8
                52      LOAD_CONST                      6: <CODE> get_dummy_mm_data
                54      MAKE_FUNCTION                   4
                56      STORE_NAME                      9: get_dummy_mm_data
                58      LOAD_CONST                      3: 'mm_counts'
                60      LOAD_NAME                       5: Mapping
                62      LOAD_NAME                       6: str
                64      LOAD_NAME                       4: int
                66      BUILD_TUPLE                     2
                68      BINARY_SUBSCR                   
                72      LOAD_CONST                      5: 'return'
                74      LOAD_NAME                       6: str
                76      BUILD_TUPLE                     4
                78      LOAD_CONST                      7: <CODE> get_dummy_text
                80      MAKE_FUNCTION                   4
                82      STORE_NAME                      10: get_dummy_text
                84      RETURN_CONST                    8: None
            [Exception Table]
        'NeMoSpeechLMDummyInputsBuilder'
        (
            'info'
            'dummy_inputs'
        )
        [Code]
            File Name: /code/NeMo/nemo/collections/speechlm2/vllm/nemotron_v3/model.py
            Object Name: NeMoSpeechLMForConditionalGeneration
            Qualified Name: NeMoSpeechLMForConditionalGeneration
            Arg Count: 0
            Pos Only Arg Count: 0
            KW Only Arg Count: 0
            Stack Size: 12
            Flags: 0x00000000
            [Names]
                '__name__'
                '__module__'
                '__qualname__'
                '__doc__'
                'classmethod'
                'str'
                'int'
                'get_placeholder_str'
                'get_mamba_state_dtype_from_config'
                'get_mamba_state_shape_from_config'
                'get_mamba_state_copy_func'
                'VllmConfig'
                '__init__'
                'NeMoSpeechLMAudioInputs'
                '_parse_audio_input'
                'tuple'
                'torch'
                'Tensor'
                '_process_audio'
                'MultiModalEmbeddings'
                'embed_multimodal'
                'IntermediateTensors'
                'forward'
                'compute_logits'
                'MultiModelKeys'
                'get_mm_mapping'
                'Iterable'
                '_nemo_to_hf_llm_weights'
                'set'
                'load_weights'
                '__classcell__'
            [Locals+Names]
                '__class__'
            [Constants]
                'NeMoSpeechLMForConditionalGeneration'
                'NeMo Speech LM model for vLLM inference.\n\n    Combines a NeMo speech encoder (AudioPerceptionModule) with a vLLM-native\n    LLM backbone (e.g. NemotronH).  Audio is encoded to embeddings that replace\n    placeholder tokens in the text sequence before LLM decoding.\n    '
                'modality'
                'i'
                'return'
                None
                [Code]
                    File Name: /code/NeMo/nemo/collections/speechlm2/vllm/nemotron_v3/model.py
                    Object Name: get_placeholder_str
                    Qualified Name: NeMoSpeechLMForConditionalGeneration.get_placeholder_str
                    Arg Count: 3
                    Pos Only Arg Count: 0
                    KW Only Arg Count: 0
                    Stack Size: 3
                    Flags: 0x00000003 (CO_OPTIMIZED | CO_NEWLOCALS)
                    [Names]
                        'startswith'
                        '_AUDIO_PLACEHOLDER'
                    [Locals+Names]
                        'cls'
                        'modality'
                        'i'
                    [Constants]
                        None
                        'audio'
                    [Disassembly]
                        0       RESUME                          0
                        2       LOAD_FAST                       1: modality
                        4       LOAD_ATTR                       1: startswith
                        24      LOAD_CONST                      1: 'audio'
                        26      CALL                            1
                        34      POP_JUMP_IF_FALSE               6 (to 48)
                        36      LOAD_GLOBAL                     2: _AUDIO_PLACEHOLDER
                        46      RETURN_VALUE                    
                        48      RETURN_CONST                    0: None
                    [Exception Table]
                [Code]
                    File Name: /code/NeMo/nemo/collections/speechlm2/vllm/nemotron_v3/model.py
                    Object Name: get_mamba_state_dtype_from_config
                    Qualified Name: NeMoSpeechLMForConditionalGeneration.get_mamba_state_dtype_from_config
                    Arg Count: 2
                    Pos Only Arg Count: 0
                    KW Only Arg Count: 0
                    Stack Size: 3
                    Flags: 0x00000003 (CO_OPTIMIZED | CO_NEWLOCALS)
                    [Names]
                        'vllm.model_executor.models.nemotron_h'
                        'NemotronHForCausalLM'
                        'get_mamba_state_dtype_from_config'
                    [Locals+Names]
                        'cls'
                        'vllm_config'
                        'NemotronHForCausalLM'
                    [Constants]
                        None
                        0
                        (
                            'NemotronHForCausalLM'
                        )
                    [Disassembly]
                        0       RESUME                          0
                        2       LOAD_CONST                      1: 0
                        4       LOAD_CONST                      2: ('NemotronHForCausalLM',)
                        6       IMPORT_NAME                     0: vllm.model_executor.models.nemotron_h
                        8       IMPORT_FROM                     1: NemotronHForCausalLM
                        10      STORE_FAST                      2: NemotronHForCausalLM
                        12      POP_TOP                         
                        14      LOAD_FAST                       2: NemotronHForCausalLM
                        16      LOAD_ATTR                       5: get_mamba_state_dtype_from_config
                        36      LOAD_FAST                       1: vllm_config
                        38      CALL                            1
                        46      RETURN_VALUE                    
                    [Exception Table]
                [Code]
                    File Name: /code/NeMo/nemo/collections/speechlm2/vllm/nemotron_v3/model.py
                    Object Name: get_mamba_state_shape_from_config
                    Qualified Name: NeMoSpeechLMForConditionalGeneration.get_mamba_state_shape_from_config
                    Arg Count: 2
                    Pos Only Arg Count: 0
                    KW Only Arg Count: 0
                    Stack Size: 3
                    Flags: 0x00000003 (CO_OPTIMIZED | CO_NEWLOCALS)
                    [Names]
                        'vllm.model_executor.models.nemotron_h'
                        'NemotronHForCausalLM'
                        'get_mamba_state_shape_from_config'
                    [Locals+Names]
                        'cls'
                        'vllm_config'
                        'NemotronHForCausalLM'
                    [Constants]
                        None
                        0
                        (
                            'NemotronHForCausalLM'
                        )
                    [Disassembly]
                        0       RESUME                          0
                        2       LOAD_CONST                      1: 0
                        4       LOAD_CONST                      2: ('NemotronHForCausalLM',)
                        6       IMPORT_NAME                     0: vllm.model_executor.models.nemotron_h
                        8       IMPORT_FROM                     1: NemotronHForCausalLM
                        10      STORE_FAST                      2: NemotronHForCausalLM
                        12      POP_TOP                         
                        14      LOAD_FAST                       2: NemotronHForCausalLM
                        16      LOAD_ATTR                       5: get_mamba_state_shape_from_config
                        36      LOAD_FAST                       1: vllm_config
                        38      CALL                            1
                        46      RETURN_VALUE                    
                    [Exception Table]
                [Code]
                    File Name: /code/NeMo/nemo/collections/speechlm2/vllm/nemotron_v3/model.py
                    Object Name: get_mamba_state_copy_func
                    Qualified Name: NeMoSpeechLMForConditionalGeneration.get_mamba_state_copy_func
                    Arg Count: 1
                    Pos Only Arg Count: 0
                    KW Only Arg Count: 0
                    Stack Size: 2
                    Flags: 0x00000003 (CO_OPTIMIZED | CO_NEWLOCALS)
                    [Names]
                        'vllm.model_executor.models.nemotron_h'
                        'NemotronHForCausalLM'
                        'get_mamba_state_copy_func'
                    [Locals+Names]
                        'cls'
                        'NemotronHForCausalLM'
                    [Constants]
                        None
                        0
                        (
                            'NemotronHForCausalLM'
                        )
                    [Disassembly]
                        0       RESUME                          0
                        2       LOAD_CONST                      1: 0
                        4       LOAD_CONST                      2: ('NemotronHForCausalLM',)
                        6       IMPORT_NAME                     0: vllm.model_executor.models.nemotron_h
                        8       IMPORT_FROM                     1: NemotronHForCausalLM
                        10      STORE_FAST                      1: NemotronHForCausalLM
                        12      POP_TOP                         
                        14      LOAD_FAST                       1: NemotronHForCausalLM
                        16      LOAD_ATTR                       5: get_mamba_state_copy_func
                        36      CALL                            0
                        44      RETURN_VALUE                    
                    [Exception Table]
                ''
                (
                    'prefix'
                )
                'vllm_config'
                'prefix'
                [Code]
                    File Name: /code/NeMo/nemo/collections/speechlm2/vllm/nemotron_v3/model.py
                    Object Name: __init__
                    Qualified Name: NeMoSpeechLMForConditionalGeneration.__init__
                    Arg Count: 1
                    Pos Only Arg Count: 0
                    KW Only Arg Count: 2
                    Stack Size: 10
                    Flags: 0x00000003 (CO_OPTIMIZED | CO_NEWLOCALS)
                    [Names]
                        'super'
                        '__init__'
                        'model_config'
                        'hf_config'
                        'config'
                        '_mark_language_model'
                        'init_vllm_registered_model'
                        'text_config'
                        'maybe_prefix'
                        'language_model'
                        'hidden_size'
                        '_mark_tower_model'
                        '_load_nemo_perception'
                        'perception'
                        'getattr'
                        'to'
                        'torch'
                        'float32'
                        'make_empty_intermediate_tensors'
                    [Locals+Names]
                        'self'
                        'vllm_config'
                        'prefix'
                        'config'
                        'llm_hidden'
                        '__class__'
                    [Constants]
                        None
                        'language_model'
                        'NemotronHForCausalLM'
                        (
                            'vllm_config'
                            'hf_config'
                            'prefix'
                            'architectures'
                        )
                        'audio'
                        'pe_encoder_path'
                        (
                            'output_dim'
                            'pe_encoder_path'
                        )
                    [Disassembly]
                        0       COPY_FREE_VARS                  1
                        2       RESUME                          0
                        4       LOAD_GLOBAL                     0: super
                        14      LOAD_DEREF                      5: __class__
                        16      LOAD_FAST                       0: self
                        18      LOAD_SUPER_ATTR                 5: __init__
                        22      CALL                            0
                        30      POP_TOP                         
                        32      LOAD_FAST                       1: vllm_config
                        34      LOAD_ATTR                       4: model_config
                        54      LOAD_ATTR                       6: hf_config
                        74      STORE_FAST                      3: config
                        76      LOAD_FAST                       3: config
                        78      LOAD_FAST                       0: self
                        80      STORE_ATTR                      4: config
                        90      LOAD_FAST                       0: self
                        92      LOAD_ATTR                       11: _mark_language_model
                        112     LOAD_FAST                       1: vllm_config
                        114     CALL                            1
                        122     BEFORE_WITH                     
                        124     POP_TOP                         
                        126     LOAD_GLOBAL                     13: NULL + init_vllm_registered_model
                        136     LOAD_FAST                       1: vllm_config
                        138     LOAD_FAST                       3: config
                        140     LOAD_ATTR                       14: text_config
                        160     LOAD_GLOBAL                     17: NULL + maybe_prefix
                        170     LOAD_FAST                       2: prefix
                        172     LOAD_CONST                      1: 'language_model'
                        174     CALL                            2
                        182     LOAD_CONST                      2: 'NemotronHForCausalLM'
                        184     BUILD_LIST                      1
                        186     KW_NAMES                        3: ('vllm_config', 'hf_config', 'prefix', 'architectures')
                        188     CALL                            4
                        196     LOAD_FAST                       0: self
                        198     STORE_ATTR                      9: language_model
                        208     LOAD_CONST                      0: None
                        210     LOAD_CONST                      0: None
                        212     LOAD_CONST                      0: None
                        214     CALL                            2
                        222     POP_TOP                         
                        224     LOAD_FAST                       3: config
                        226     LOAD_ATTR                       14: text_config
                        246     LOAD_ATTR                       20: hidden_size
                        266     STORE_FAST                      4: llm_hidden
                        268     LOAD_FAST                       0: self
                        270     LOAD_ATTR                       23: _mark_tower_model
                        290     LOAD_FAST                       1: vllm_config
                        292     LOAD_CONST                      4: 'audio'
                        294     BUILD_SET                       1
                        296     CALL                            2
                        304     BEFORE_WITH                     
                        306     POP_TOP                         
                        308     LOAD_GLOBAL                     25: NULL + _load_nemo_perception
                        318     LOAD_FAST                       3: config
                        320     LOAD_ATTR                       26: perception
                        340     LOAD_FAST                       4: llm_hidden
                        342     LOAD_GLOBAL                     29: NULL + getattr
                        352     LOAD_FAST                       3: config
                        354     LOAD_CONST                      5: 'pe_encoder_path'
                        356     LOAD_CONST                      0: None
                        358     CALL                            3
                        366     KW_NAMES                        6: ('output_dim', 'pe_encoder_path')
                        368     CALL                            3
                        376     LOAD_FAST                       0: self
                        378     STORE_ATTR                      13: perception
                        388     LOAD_FAST                       0: self
                        390     LOAD_ATTR                       26: perception
                        410     LOAD_ATTR                       31: to
                        430     LOAD_GLOBAL                     32: torch
                        440     LOAD_ATTR                       34: float32
                        460     CALL                            1
                        468     LOAD_FAST                       0: self
                        470     STORE_ATTR                      13: perception
                        480     LOAD_CONST                      0: None
                        482     LOAD_CONST                      0: None
                        484     LOAD_CONST                      0: None
                        486     CALL                            2
                        494     POP_TOP                         
                        496     LOAD_FAST                       0: self
                        498     LOAD_ATTR                       18: language_model
                        518     LOAD_ATTR                       36: make_empty_intermediate_tensors
                        538     LOAD_FAST                       0: self
                        540     STORE_ATTR                      18: make_empty_intermediate_tensors
                        550     RETURN_CONST                    0: None
                        552     PUSH_EXC_INFO                   
                        554     WITH_EXCEPT_START               
                        556     POP_JUMP_IF_TRUE                1 (to 560)
                        558     RERAISE                         2
                        560     POP_TOP                         
                        562     POP_EXCEPT                      
                        564     POP_TOP                         
                        566     POP_TOP                         
                        568     JUMP_BACKWARD                   173 (to 224)
                        570     COPY                            3
                        572     POP_EXCEPT                      
                        574     RERAISE                         1
                        576     PUSH_EXC_INFO                   
                        578     WITH_EXCEPT_START               
                        580     POP_JUMP_IF_TRUE                1 (to 584)
                        582     RERAISE                         2
                        584     POP_TOP                         
                        586     POP_EXCEPT                      
                        588     POP_TOP                         
                        590     POP_TOP                         
                        592     JUMP_BACKWARD                   49 (to 496)
                        594     COPY                            3
                        596     POP_EXCEPT                      
                        598     RERAISE                         1
                    [Exception Table]
                        124 to 208 -> 552 [1] lasti
                        306 to 480 -> 576 [1] lasti
                        552 to 562 -> 570 [3] lasti
                        576 to 586 -> 594 [3] lasti
                [Code]
                    File Name: /code/NeMo/nemo/collections/speechlm2/vllm/nemotron_v3/model.py
                    Object Name: _parse_audio_input
                    Qualified Name: NeMoSpeechLMForConditionalGeneration._parse_audio_input
                    Arg Count: 1
                    Pos Only Arg Count: 0
                    KW Only Arg Count: 0
                    Stack Size: 10
                    Flags: 0x0000000B (CO_OPTIMIZED | CO_NEWLOCALS | CO_VARKEYWORDS)
                    [Names]
                        'pop'
                        'isinstance'
                        'list'
                        'max'
                        'torch'
                        'nn'
                        'functional'
                        'pad'
                        'shape'
                        'stack'
                        'tensor'
                        'Tensor'
                        'NeMoSpeechLMAudioInputs'
                    [Locals+Names]
                        'self'
                        'kwargs'
                        'audio_signal'
                        'audio_signal_length'
                        'max_len'
                        'a'
                        'padded'
                    [Constants]
                        None
                        'audio_signal'
                        'audio_signal_length'
                        [Code]
                            File Name: /code/NeMo/nemo/collections/speechlm2/vllm/nemotron_v3/model.py
                            Object Name: <genexpr>
                            Qualified Name: NeMoSpeechLMForConditionalGeneration._parse_audio_input.<locals>.<genexpr>
                            Arg Count: 1
                            Pos Only Arg Count: 0
                            KW Only Arg Count: 0
                            Stack Size: 3
                            Flags: 0x00000033 (CO_OPTIMIZED | CO_NEWLOCALS | CO_NESTED | CO_GENERATOR)
                            [Names]
                                'shape'
                            [Locals+Names]
                                '.0'
                                'a'
                            [Constants]
                                -1
                                None
                            [Disassembly]
                                0       RETURN_GENERATOR                
                                2       POP_TOP                         
                                4       RESUME                          0
                                6       LOAD_FAST                       0: .0
                                8       FOR_ITER                        19 (to 48)
                                12      STORE_FAST                      1: a
                                14      LOAD_FAST                       1: a
                                16      LOAD_ATTR                       0: shape
                                36      LOAD_CONST                      0: -1
                                38      BINARY_SUBSCR                   
                                42      YIELD_VALUE                     1
                                44      RESUME                          1
                                46      POP_TOP                         
                                48      JUMP_BACKWARD                   21 (to 8)
                                50      END_FOR                         
                                52      RETURN_CONST                    1: None
                                54      CALL_INTRINSIC_1                3 (INTRINSIC_STOPITERATION_ERROR)
                                56      RERAISE                         1
                            [Exception Table]
                                4 to 54 -> 54 [0] lasti
                        0
                        -1
                        (
                            'dim'
                        )
                        (
                            'audio_signal'
                            'audio_signal_length'
                        )
                    [Disassembly]
                        0       RESUME                          0
                        2       LOAD_FAST                       1: kwargs
                        4       LOAD_ATTR                       1: pop
                        24      LOAD_CONST                      1: 'audio_signal'
                        26      LOAD_CONST                      0: None
                        28      CALL                            2
                        36      STORE_FAST                      2: audio_signal
                        38      LOAD_FAST                       2: audio_signal
                        40      POP_JUMP_IF_NOT_NONE            1 (to 44)
                        42      RETURN_CONST                    0: None
                        44      LOAD_FAST                       1: kwargs
                        46      LOAD_ATTR                       1: pop
                        66      LOAD_CONST                      2: 'audio_signal_length'
                        68      LOAD_CONST                      0: None
                        70      CALL                            2
                        78      STORE_FAST                      3: audio_signal_length
                        80      LOAD_GLOBAL                     3: NULL + isinstance
                        90      LOAD_FAST                       2: audio_signal
                        92      LOAD_GLOBAL                     4: list
                        102     CALL                            2
                        110     POP_JUMP_IF_FALSE               114 (to 340)
                        112     LOAD_GLOBAL                     7: NULL + max
                        122     LOAD_CONST                      3: <CODE> <genexpr>
                        124     MAKE_FUNCTION                   0
                        126     LOAD_FAST                       2: audio_signal
                        128     GET_ITER                        
                        130     CALL                            0
                        138     CALL                            1
                        146     STORE_FAST                      4: max_len
                        148     LOAD_FAST                       2: audio_signal
                        150     GET_ITER                        
                        152     LOAD_FAST_AND_CLEAR             5: a
                        154     SWAP                            2
                        156     BUILD_LIST                      0
                        158     SWAP                            2
                        160     FOR_ITER                        62 (to 286)
                        164     STORE_FAST                      5: a
                        166     LOAD_GLOBAL                     8: torch
                        176     LOAD_ATTR                       10: nn
                        196     LOAD_ATTR                       12: functional
                        216     LOAD_ATTR                       15: pad
                        236     LOAD_FAST                       5: a
                        238     LOAD_CONST                      4: 0
                        240     LOAD_FAST                       4: max_len
                        242     LOAD_FAST                       5: a
                        244     LOAD_ATTR                       16: shape
                        264     LOAD_CONST                      5: -1
                        266     BINARY_SUBSCR                   
                        270     BINARY_OP                       10 (-)
                        274     BUILD_TUPLE                     2
                        276     CALL                            2
                        284     LIST_APPEND                     2
                        286     JUMP_BACKWARD                   64 (to 160)
                        288     END_FOR                         
                        290     STORE_FAST                      6: padded
                        292     STORE_FAST                      5: a
                        294     LOAD_GLOBAL                     9: NULL + torch
                        304     LOAD_ATTR                       18: stack
                        324     LOAD_FAST                       6: padded
                        326     LOAD_CONST                      4: 0
                        328     KW_NAMES                        6: ('dim',)
                        330     CALL                            2
                        338     STORE_FAST                      2: audio_signal
                        340     LOAD_FAST                       3: audio_signal_length
                        342     POP_JUMP_IF_NOT_NONE            52 (to 448)
                        344     LOAD_GLOBAL                     9: NULL + torch
                        354     LOAD_ATTR                       20: tensor
                        374     LOAD_FAST                       2: audio_signal
                        376     LOAD_ATTR                       16: shape
                        396     LOAD_CONST                      5: -1
                        398     BINARY_SUBSCR                   
                        402     BUILD_LIST                      1
                        404     LOAD_FAST                       2: audio_signal
                        406     LOAD_ATTR                       16: shape
                        426     LOAD_CONST                      4: 0
                        428     BINARY_SUBSCR                   
                        432     BINARY_OP                       5 (*)
                        436     CALL                            1
                        444     STORE_FAST                      3: audio_signal_length
                        446     JUMP_FORWARD                    47 (to 542)
                        448     LOAD_GLOBAL                     3: NULL + isinstance
                        458     LOAD_FAST                       3: audio_signal_length
                        460     LOAD_GLOBAL                     8: torch
                        470     LOAD_ATTR                       22: Tensor
                        490     CALL                            2
                        498     POP_JUMP_IF_TRUE                21 (to 542)
                        500     LOAD_GLOBAL                     9: NULL + torch
                        510     LOAD_ATTR                       20: tensor
                        530     LOAD_FAST                       3: audio_signal_length
                        532     CALL                            1
                        540     STORE_FAST                      3: audio_signal_length
                        542     LOAD_GLOBAL                     25: NULL + NeMoSpeechLMAudioInputs
                        552     LOAD_FAST                       2: audio_signal
                        554     LOAD_FAST                       3: audio_signal_length
                        556     KW_NAMES                        7: ('audio_signal', 'audio_signal_length')
                        558     CALL                            2
                        566     RETURN_VALUE                    
                        568     SWAP                            2
                        570     POP_TOP                         
                        572     SWAP                            2
                        574     STORE_FAST                      5: a
                        576     RERAISE                         0
                    [Exception Table]
                        156 to 290 -> 568 [2] 
                'audio_input'
                ...
                [Code]
                    File Name: /code/NeMo/nemo/collections/speechlm2/vllm/nemotron_v3/model.py
                    Object Name: _process_audio
                    Qualified Name: NeMoSpeechLMForConditionalGeneration._process_audio
                    Arg Count: 2
                    Pos Only Arg Count: 0
                    KW Only Arg Count: 0
                    Stack Size: 7
                    Flags: 0x00000003 (CO_OPTIMIZED | CO_NEWLOCALS)
                    [Names]
                        'next'
                        'language_model'
                        'parameters'
                        'device'
                        'StopIteration'
                        'perception'
                        'to'
                        'audio_signal'
                        'isinstance'
                        'list'
                        'torch'
                        'stack'
                        'float32'
                        'audio_signal_length'
                        'no_grad'
                        'bfloat16'
                        'tuple'
                        'range'
                        'shape'
                    [Locals+Names]
                        'self'
                        'audio_input'
                        'device'
                        'audio_signal'
                        'audio_lengths'
                        'audio_embed_lens'
                        'audio_embeds'
                    [Constants]
                        None
                        0
                        (
                            'dim'
                        )
                        (
                            'device'
                            'dtype'
                        )
                        (
                            'device'
                        )
                        (
                            'input_signal'
                            'input_signal_length'
                        )
                        [Code]
                            File Name: /code/NeMo/nemo/collections/speechlm2/vllm/nemotron_v3/model.py
                            Object Name: <genexpr>
                            Qualified Name: NeMoSpeechLMForConditionalGeneration._process_audio.<locals>.<genexpr>
                            Arg Count: 1
                            Pos Only Arg Count: 0
                            KW Only Arg Count: 0
                            Stack Size: 6
                            Flags: 0x00000033 (CO_OPTIMIZED | CO_NEWLOCALS | CO_NESTED | CO_GENERATOR)
                            [Names]
                            [Locals+Names]
                                '.0'
                                'i'
                                'audio_embed_lens'
                                'audio_embeds'
                            [Constants]
                                None
                            [Disassembly]
                                0       COPY_FREE_VARS                  2
                                2       RETURN_GENERATOR                
                                4       POP_TOP                         
                                6       RESUME                          0
                                8       LOAD_FAST                       0: .0
                                10      FOR_ITER                        16 (to 44)
                                14      STORE_FAST                      1: i
                                16      LOAD_DEREF                      3: audio_embeds
                                18      LOAD_FAST                       1: i
                                20      LOAD_CONST                      0: None
                                22      LOAD_DEREF                      2: audio_embed_lens
                                24      LOAD_FAST                       1: i
                                26      BINARY_SUBSCR                   
                                30      BUILD_SLICE                     2
                                32      BUILD_TUPLE                     2
                                34      BINARY_SUBSCR                   
                                38      YIELD_VALUE                     1
                                40      RESUME                          1
                                42      POP_TOP                         
                                44      JUMP_BACKWARD                   18 (to 10)
                                46      END_FOR                         
                                48      RETURN_CONST                    0: None
                                50      CALL_INTRINSIC_1                3 (INTRINSIC_STOPITERATION_ERROR)
                                52      RERAISE                         1
                            [Exception Table]
                                6 to 50 -> 50 [0] lasti
                    [Disassembly]
                        0       MAKE_CELL                       5: audio_embed_lens
                        2       MAKE_CELL                       6: audio_embeds
                        4       RESUME                          0
                        6       NOP                             
                        8       LOAD_GLOBAL                     1: NULL + next
                        18      LOAD_FAST                       0: self
                        20      LOAD_ATTR                       2: language_model
                        40      LOAD_ATTR                       5: parameters
                        60      CALL                            0
                        68      CALL                            1
                        76      LOAD_ATTR                       6: device
                        96      STORE_FAST                      2: device
                        98      LOAD_GLOBAL                     1: NULL + next
                        108     LOAD_FAST                       0: self
                        110     LOAD_ATTR                       10: perception
                        130     LOAD_ATTR                       5: parameters
                        150     CALL                            0
                        158     CALL                            1
                        166     LOAD_ATTR                       6: device
                        186     LOAD_FAST                       2: device
                        188     COMPARE_OP                      55 (!=)
                        192     POP_JUMP_IF_FALSE               32 (to 258)
                        194     LOAD_FAST                       0: self
                        196     LOAD_ATTR                       10: perception
                        216     LOAD_ATTR                       13: to
                        236     LOAD_FAST                       2: device
                        238     CALL                            1
                        246     LOAD_FAST                       0: self
                        248     STORE_ATTR                      5: perception
                        258     LOAD_FAST                       1: audio_input
                        260     LOAD_ATTR                       14: audio_signal
                        280     STORE_FAST                      3: audio_signal
                        282     LOAD_GLOBAL                     17: NULL + isinstance
                        292     LOAD_FAST                       3: audio_signal
                        294     LOAD_GLOBAL                     18: list
                        304     CALL                            2
                        312     POP_JUMP_IF_FALSE               23 (to 360)
                        314     LOAD_GLOBAL                     21: NULL + torch
                        324     LOAD_ATTR                       22: stack
                        344     LOAD_FAST                       3: audio_signal
                        346     LOAD_CONST                      1: 0
                        348     KW_NAMES                        2: ('dim',)
                        350     CALL                            2
                        358     STORE_FAST                      3: audio_signal
                        360     LOAD_FAST                       3: audio_signal
                        362     LOAD_ATTR                       13: to
                        382     LOAD_FAST                       2: device
                        384     LOAD_GLOBAL                     20: torch
                        394     LOAD_ATTR                       24: float32
                        414     KW_NAMES                        3: ('device', 'dtype')
                        416     CALL                            2
                        424     STORE_FAST                      3: audio_signal
                        426     LOAD_FAST                       1: audio_input
                        428     LOAD_ATTR                       26: audio_signal_length
                        448     LOAD_ATTR                       13: to
                        468     LOAD_FAST                       2: device
                        470     KW_NAMES                        4: ('device',)
                        472     CALL                            1
                        480     STORE_FAST                      4: audio_lengths
                        482     LOAD_GLOBAL                     21: NULL + torch
                        492     LOAD_ATTR                       28: no_grad
                        512     CALL                            0
                        520     BEFORE_WITH                     
                        522     POP_TOP                         
                        524     LOAD_FAST                       0: self
                        526     LOAD_ATTR                       11: perception
                        546     LOAD_FAST                       3: audio_signal
                        548     LOAD_FAST                       4: audio_lengths
                        550     KW_NAMES                        5: ('input_signal', 'input_signal_length')
                        552     CALL                            2
                        560     UNPACK_SEQUENCE                 2
                        564     STORE_DEREF                     6: audio_embeds
                        566     STORE_DEREF                     5: audio_embed_lens
                        568     LOAD_CONST                      0: None
                        570     LOAD_CONST                      0: None
                        572     LOAD_CONST                      0: None
                        574     CALL                            2
                        582     POP_TOP                         
                        584     LOAD_DEREF                      6: audio_embeds
                        586     LOAD_ATTR                       13: to
                        606     LOAD_FAST                       2: device
                        608     LOAD_GLOBAL                     20: torch
                        618     LOAD_ATTR                       30: bfloat16
                        638     KW_NAMES                        3: ('device', 'dtype')
                        640     CALL                            2
                        648     STORE_DEREF                     6: audio_embeds
                        650     LOAD_GLOBAL                     33: NULL + tuple
                        660     LOAD_CLOSURE                    5: audio_embed_lens
                        662     LOAD_CLOSURE                    6: audio_embeds
                        664     BUILD_TUPLE                     2
                        666     LOAD_CONST                      6: <CODE> <genexpr>
                        668     MAKE_FUNCTION                   8
                        670     LOAD_GLOBAL                     35: NULL + range
                        680     LOAD_DEREF                      6: audio_embeds
                        682     LOAD_ATTR                       36: shape
                        702     LOAD_CONST                      1: 0
                        704     BINARY_SUBSCR                   
                        708     CALL                            1
                        716     GET_ITER                        
                        718     CALL                            0
                        726     CALL                            1
                        734     RETURN_VALUE                    
                        736     PUSH_EXC_INFO                   
                        738     LOAD_GLOBAL                     8: StopIteration
                        748     CHECK_EXC_MATCH                 
                        750     POP_JUMP_IF_FALSE               49 (to 850)
                        752     POP_TOP                         
                        754     LOAD_GLOBAL                     1: NULL + next
                        764     LOAD_FAST                       0: self
                        766     LOAD_ATTR                       10: perception
                        786     LOAD_ATTR                       5: parameters
                        806     CALL                            0
                        814     CALL                            1
                        822     LOAD_ATTR                       6: device
                        842     STORE_FAST                      2: device
                        844     POP_EXCEPT                      
                        846     JUMP_BACKWARD                   376 (to 98)
                        850     RERAISE                         0
                        852     COPY                            3
                        854     POP_EXCEPT                      
                        856     RERAISE                         1
                        858     PUSH_EXC_INFO                   
                        860     WITH_EXCEPT_START               
                        862     POP_JUMP_IF_TRUE                1 (to 866)
                        864     RERAISE                         2
                        866     POP_TOP                         
                        868     POP_EXCEPT                      
                        870     POP_TOP                         
                        872     POP_TOP                         
                        874     JUMP_BACKWARD                   146 (to 584)
                        876     COPY                            3
                        878     POP_EXCEPT                      
                        880     RERAISE                         1
                    [Exception Table]
                        8 to 98 -> 736 [0] 
                        522 to 568 -> 858 [1] lasti
                        736 to 844 -> 852 [1] lasti
                        850 to 852 -> 852 [1] lasti
                        858 to 868 -> 876 [3] lasti
                [Code]
                    File Name: /code/NeMo/nemo/collections/speechlm2/vllm/nemotron_v3/model.py
                    Object Name: embed_multimodal
                    Qualified Name: NeMoSpeechLMForConditionalGeneration.embed_multimodal
                    Arg Count: 1
                    Pos Only Arg Count: 0
                    KW Only Arg Count: 0
                    Stack Size: 5
                    Flags: 0x0000000B (CO_OPTIMIZED | CO_NEWLOCALS | CO_VARKEYWORDS)
                    [Names]
                        '_parse_audio_input'
                        '_process_audio'
                    [Locals+Names]
                        'self'
                        'kwargs'
                        'audio_input'
                    [Constants]
                        None
                        (
                        )
                    [Disassembly]
                        0       RESUME                          0
                        2       PUSH_NULL                       
                        4       LOAD_FAST                       0: self
                        6       LOAD_ATTR                       0: _parse_audio_input
                        26      LOAD_CONST                      1: ()
                        28      BUILD_MAP                       0
                        30      LOAD_FAST                       1: kwargs
                        32      DICT_MERGE                      1
                        34      CALL_FUNCTION_EX                1
                        36      STORE_FAST                      2: audio_input
                        38      LOAD_FAST                       2: audio_input
                        40      POP_JUMP_IF_NOT_NONE            2 (to 46)
                        42      BUILD_LIST                      0
                        44      RETURN_VALUE                    
                        46      LOAD_FAST                       0: self
                        48      LOAD_ATTR                       3: _process_audio
                        68      LOAD_FAST                       2: audio_input
                        70      CALL                            1
                        78      RETURN_VALUE                    
                    [Exception Table]
                'input_ids'
                'positions'
                'intermediate_tensors'
                'inputs_embeds'
                [Code]
                    File Name: /code/NeMo/nemo/collections/speechlm2/vllm/nemotron_v3/model.py
                    Object Name: forward
                    Qualified Name: NeMoSpeechLMForConditionalGeneration.forward
                    Arg Count: 5
                    Pos Only Arg Count: 0
                    KW Only Arg Count: 0
                    Stack Size: 6
                    Flags: 0x0000000B (CO_OPTIMIZED | CO_NEWLOCALS | CO_VARKEYWORDS)
                    [Names]
                        'language_model'
                    [Locals+Names]
                        'self'
                        'input_ids'
                        'positions'
                        'intermediate_tensors'
                        'inputs_embeds'
                        'kwargs'
                    [Constants]
                        None
                    [Disassembly]
                        0       RESUME                          0
                        2       LOAD_FAST                       3: intermediate_tensors
                        4       POP_JUMP_IF_NONE                2 (to 10)
                        6       LOAD_CONST                      0: None
                        8       STORE_FAST                      4: inputs_embeds
                        10      LOAD_FAST                       0: self
                        12      LOAD_ATTR                       1: language_model
                        32      LOAD_FAST                       1: input_ids
                        34      LOAD_FAST                       2: positions
                        36      LOAD_FAST                       3: intermediate_tensors
                        38      LOAD_FAST                       4: inputs_embeds
                        40      CALL                            4
                        48      RETURN_VALUE                    
                    [Exception Table]
                'hidden_states'
                [Code]
                    File Name: /code/NeMo/nemo/collections/speechlm2/vllm/nemotron_v3/model.py
                    Object Name: compute_logits
                    Qualified Name: NeMoSpeechLMForConditionalGeneration.compute_logits
                    Arg Count: 2
                    Pos Only Arg Count: 0
                    KW Only Arg Count: 0
                    Stack Size: 3
                    Flags: 0x00000003 (CO_OPTIMIZED | CO_NEWLOCALS)
                    [Names]
                        'language_model'
                        'compute_logits'
                    [Locals+Names]
                        'self'
                        'hidden_states'
                    [Constants]
                        None
                    [Disassembly]
                        0       RESUME                          0
                        2       LOAD_FAST                       0: self
                        4       LOAD_ATTR                       0: language_model
                        24      LOAD_ATTR                       3: compute_logits
                        44      LOAD_FAST                       1: hidden_states
                        46      CALL                            1
                        54      RETURN_VALUE                    
                    [Exception Table]
                [Code]
                    File Name: /code/NeMo/nemo/collections/speechlm2/vllm/nemotron_v3/model.py
                    Object Name: get_mm_mapping
                    Qualified Name: NeMoSpeechLMForConditionalGeneration.get_mm_mapping
                    Arg Count: 1
                    Pos Only Arg Count: 0
                    KW Only Arg Count: 0
                    Stack Size: 5
                    Flags: 0x00000003 (CO_OPTIMIZED | CO_NEWLOCALS)
                    [Names]
                        'MultiModelKeys'
                        'from_string_field'
                    [Locals+Names]
                        'self'
                    [Constants]
                        None
                        'language_model'
                        'perception.proj'
                        'perception.encoder'
                        (
                            'language_model'
                            'connector'
                            'tower_model'
                        )
                    [Disassembly]
                        0       RESUME                          0
                        2       LOAD_GLOBAL                     1: NULL + MultiModelKeys
                        12      LOAD_ATTR                       2: from_string_field
                        32      LOAD_CONST                      1: 'language_model'
                        34      LOAD_CONST                      2: 'perception.proj'
                        36      LOAD_CONST                      3: 'perception.encoder'
                        38      KW_NAMES                        4: ('language_model', 'connector', 'tower_model')
                        40      CALL                            3
                        48      RETURN_VALUE                    
                    [Exception Table]
                'weights'
                [Code]
                    File Name: /code/NeMo/nemo/collections/speechlm2/vllm/nemotron_v3/model.py
                    Object Name: _nemo_to_hf_llm_weights
                    Qualified Name: NeMoSpeechLMForConditionalGeneration._nemo_to_hf_llm_weights
                    Arg Count: 2
                    Pos Only Arg Count: 0
                    KW Only Arg Count: 0
                    Stack Size: 7
                    Flags: 0x00000023 (CO_OPTIMIZED | CO_NEWLOCALS | CO_GENERATOR)
                    [Names]
                        'replace'
                        'endswith'
                        'shape'
                        'range'
                        't'
                        'getattr'
                        'config'
                        'text_config'
                        'torch'
                        'zeros'
                        'dtype'
                        'cat'
                    [Locals+Names]
                        'self'
                        'weights'
                        'name'
                        'tensor'
                        'hf_name'
                        'prefix'
                        'n_experts'
                        'i'
                        'target_vocab'
                        'pad'
                    [Constants]
                        "Convert NeMo checkpoint weight names to HuggingFace NemotronH\n        format that vLLM's NemotronHForCausalLM.load_weights() expects."
                        'llm.model.'
                        'backbone.'
                        'llm.lm_head'
                        'lm_head'
                        'backbone.norm.weight'
                        'backbone.norm_f.weight'
                        '.experts.down_projs'
                        ''
                        0
                        '.experts.'
                        '.down_proj.weight'
                        '.experts.gate_and_up_projs'
                        '.up_proj.weight'
                        (
                            'backbone.embed_tokens.weight'
                            'lm_head.weight'
                        )
                        'vocab_size'
                        1
                        None
                        'dtype'
                        (
                            'dim'
                        )
                    [Disassembly]
                        0       RETURN_GENERATOR                
                        2       POP_TOP                         
                        4       RESUME                          0
                        6       LOAD_FAST                       1: weights
                        8       GET_ITER                        
                        10      FOR_ITER                        412 (to 838)
                        16      UNPACK_SEQUENCE                 2
                        20      STORE_FAST                      2: name
                        22      STORE_FAST                      3: tensor
                        24      LOAD_FAST                       2: name
                        26      LOAD_ATTR                       1: replace
                        46      LOAD_CONST                      1: 'llm.model.'
                        48      LOAD_CONST                      2: 'backbone.'
                        50      CALL                            2
                        58      STORE_FAST                      4: hf_name
                        60      LOAD_FAST                       4: hf_name
                        62      LOAD_ATTR                       1: replace
                        82      LOAD_CONST                      3: 'llm.lm_head'
                        84      LOAD_CONST                      4: 'lm_head'
                        86      CALL                            2
                        94      STORE_FAST                      4: hf_name
                        96      LOAD_FAST                       4: hf_name
                        98      LOAD_CONST                      5: 'backbone.norm.weight'
                        100     COMPARE_OP                      40 (==)
                        104     POP_JUMP_IF_FALSE               2 (to 110)
                        106     LOAD_CONST                      6: 'backbone.norm_f.weight'
                        108     STORE_FAST                      4: hf_name
                        110     LOAD_FAST                       4: hf_name
                        112     LOAD_ATTR                       3: endswith
                        132     LOAD_CONST                      7: '.experts.down_projs'
                        134     CALL                            1
                        142     POP_JUMP_IF_FALSE               79 (to 302)
                        144     LOAD_FAST                       4: hf_name
                        146     LOAD_ATTR                       1: replace
                        166     LOAD_CONST                      7: '.experts.down_projs'
                        168     LOAD_CONST                      8: ''
                        170     CALL                            2
                        178     STORE_FAST                      5: prefix
                        180     LOAD_FAST                       3: tensor
                        182     LOAD_ATTR                       4: shape
                        202     LOAD_CONST                      9: 0
                        204     BINARY_SUBSCR                   
                        208     STORE_FAST                      6: n_experts
                        210     LOAD_GLOBAL                     7: NULL + range
                        220     LOAD_FAST                       6: n_experts
                        222     CALL                            1
                        230     GET_ITER                        
                        232     FOR_ITER                        31 (to 296)
                        236     STORE_FAST                      7: i
                        238     LOAD_FAST                       5: prefix
                        240     FORMAT_VALUE                    0 (FVC_NONE)
                        242     LOAD_CONST                      10: '.experts.'
                        244     LOAD_FAST                       7: i
                        246     FORMAT_VALUE                    0 (FVC_NONE)
                        248     LOAD_CONST                      11: '.down_proj.weight'
                        250     BUILD_STRING                    4
                        252     LOAD_FAST                       3: tensor
                        254     LOAD_FAST                       7: i
                        256     BINARY_SUBSCR                   
                        260     LOAD_ATTR                       9: t
                        280     CALL                            0
                        288     BUILD_TUPLE                     2
                        290     YIELD_VALUE                     1
                        292     RESUME                          1
                        294     POP_TOP                         
                        296     JUMP_BACKWARD                   33 (to 232)
                        298     END_FOR                         
                        300     JUMP_BACKWARD                   146 (to 10)
                        302     LOAD_FAST                       4: hf_name
                        304     LOAD_ATTR                       3: endswith
                        324     LOAD_CONST                      12: '.experts.gate_and_up_projs'
                        326     CALL                            1
                        334     POP_JUMP_IF_FALSE               79 (to 494)
                        336     LOAD_FAST                       4: hf_name
                        338     LOAD_ATTR                       1: replace
                        358     LOAD_CONST                      12: '.experts.gate_and_up_projs'
                        360     LOAD_CONST                      8: ''
                        362     CALL                            2
                        370     STORE_FAST                      5: prefix
                        372     LOAD_FAST                       3: tensor
                        374     LOAD_ATTR                       4: shape
                        394     LOAD_CONST                      9: 0
                        396     BINARY_SUBSCR                   
                        400     STORE_FAST                      6: n_experts
                        402     LOAD_GLOBAL                     7: NULL + range
                        412     LOAD_FAST                       6: n_experts
                        414     CALL                            1
                        422     GET_ITER                        
                        424     FOR_ITER                        31 (to 488)
                        428     STORE_FAST                      7: i
                        430     LOAD_FAST                       5: prefix
                        432     FORMAT_VALUE                    0 (FVC_NONE)
                        434     LOAD_CONST                      10: '.experts.'
                        436     LOAD_FAST                       7: i
                        438     FORMAT_VALUE                    0 (FVC_NONE)
                        440     LOAD_CONST                      13: '.up_proj.weight'
                        442     BUILD_STRING                    4
                        444     LOAD_FAST                       3: tensor
                        446     LOAD_FAST                       7: i
                        448     BINARY_SUBSCR                   
                        452     LOAD_ATTR                       9: t
                        472     CALL                            0
                        480     BUILD_TUPLE                     2
                        482     YIELD_VALUE                     1
                        484     RESUME                          1
                        486     POP_TOP                         
                        488     JUMP_BACKWARD                   33 (to 424)
                        490     END_FOR                         
                        492     JUMP_BACKWARD                   242 (to 10)
                        494     LOAD_FAST                       4: hf_name
                        496     LOAD_CONST                      14: ('backbone.embed_tokens.weight', 'lm_head.weight')
                        498     CONTAINS_OP                     0 (in)
                        500     POP_JUMP_IF_FALSE               161 (to 824)
                        502     LOAD_GLOBAL                     11: NULL + getattr
                        512     LOAD_FAST                       0: self
                        514     LOAD_ATTR                       12: config
                        534     LOAD_ATTR                       14: text_config
                        554     LOAD_CONST                      15: 'vocab_size'
                        556     LOAD_FAST                       3: tensor
                        558     LOAD_ATTR                       4: shape
                        578     LOAD_CONST                      9: 0
                        580     BINARY_SUBSCR                   
                        584     CALL                            3
                        592     STORE_FAST                      8: target_vocab
                        594     LOAD_FAST                       3: tensor
                        596     LOAD_ATTR                       4: shape
                        616     LOAD_CONST                      9: 0
                        618     BINARY_SUBSCR                   
                        622     LOAD_FAST                       8: target_vocab
                        624     COMPARE_OP                      2 (<)
                        628     POP_JUMP_IF_FALSE               89 (to 808)
                        630     LOAD_GLOBAL                     17: NULL + torch
                        640     LOAD_ATTR                       18: zeros
                        660     LOAD_FAST                       8: target_vocab
                        662     LOAD_FAST                       3: tensor
                        664     LOAD_ATTR                       4: shape
                        684     LOAD_CONST                      9: 0
                        686     BINARY_SUBSCR                   
                        690     BINARY_OP                       10 (-)
                        694     BUILD_LIST                      1
                        696     LOAD_FAST                       3: tensor
                        698     LOAD_ATTR                       4: shape
                        718     LOAD_CONST                      16: 1
                        720     LOAD_CONST                      17: None
                        722     BINARY_SLICE                    
                        724     LIST_EXTEND                     1
                        726     CALL_INTRINSIC_1                6 (INTRINSIC_LIST_TO_TUPLE)
                        728     LOAD_CONST                      18: 'dtype'
                        730     LOAD_FAST                       3: tensor
                        732     LOAD_ATTR                       20: dtype
                        752     BUILD_MAP                       1
                        754     CALL_FUNCTION_EX                1
                        756     STORE_FAST                      9: pad
                        758     LOAD_GLOBAL                     17: NULL + torch
                        768     LOAD_ATTR                       22: cat
                        788     LOAD_FAST                       3: tensor
                        790     LOAD_FAST                       9: pad
                        792     BUILD_LIST                      2
                        794     LOAD_CONST                      9: 0
                        796     KW_NAMES                        19: ('dim',)
                        798     CALL                            2
                        806     STORE_FAST                      3: tensor
                        808     LOAD_FAST                       4: hf_name
                        810     LOAD_FAST                       3: tensor
                        812     BUILD_TUPLE                     2
                        814     YIELD_VALUE                     1
                        816     RESUME                          1
                        818     POP_TOP                         
                        820     JUMP_BACKWARD                   407 (to 10)
                        824     LOAD_FAST                       4: hf_name
                        826     LOAD_FAST                       3: tensor
                        828     BUILD_TUPLE                     2
                        830     YIELD_VALUE                     1
                        832     RESUME                          1
                        834     POP_TOP                         
                        836     JUMP_BACKWARD                   415 (to 10)
                        840     END_FOR                         
                        842     RETURN_CONST                    17: None
                        844     CALL_INTRINSIC_1                3 (INTRINSIC_STOPITERATION_ERROR)
                        846     RERAISE                         1
                    [Exception Table]
                        4 to 844 -> 844 [0] lasti
                [Code]
                    File Name: /code/NeMo/nemo/collections/speechlm2/vllm/nemotron_v3/model.py
                    Object Name: load_weights
                    Qualified Name: NeMoSpeechLMForConditionalGeneration.load_weights
                    Arg Count: 2
                    Pos Only Arg Count: 0
                    KW Only Arg Count: 0
                    Stack Size: 7
                    Flags: 0x00000003 (CO_OPTIMIZED | CO_NEWLOCALS)
                    [Names]
                        'startswith'
                        'len'
                        'append'
                        'items'
                        'float'
                        'perception'
                        'load_state_dict'
                        'to'
                        'torch'
                        'float32'
                        '_nemo_to_hf_llm_weights'
                        'AutoWeightsLoader'
                        'load_weights'
                    [Locals+Names]
                        'self'
                        'weights'
                        'perception_weights'
                        'perception_prefix'
                        'llm_raw'
                        'name'
                        'tensor'
                        'key'
                        'k'
                        'v'
                        'float32_weights'
                        'loaded_perception'
                        'hf_weights'
                        'combined'
                        'loader'
                        'loaded_llm'
                    [Constants]
                        None
                        'perception.'
                        '._extra_state'
                        False
                        (
                            'strict'
                        )
                        [Code]
                            File Name: /code/NeMo/nemo/collections/speechlm2/vllm/nemotron_v3/model.py
                            Object Name: <genexpr>
                            Qualified Name: NeMoSpeechLMForConditionalGeneration.load_weights.<locals>.<genexpr>
                            Arg Count: 1
                            Pos Only Arg Count: 0
                            KW Only Arg Count: 0
                            Stack Size: 3
                            Flags: 0x00000033 (CO_OPTIMIZED | CO_NEWLOCALS | CO_NESTED | CO_GENERATOR)
                            [Names]
                            [Locals+Names]
                                '.0'
                                'n'
                                't'
                            [Constants]
                                'language_model.'
                                None
                            [Disassembly]
                                0       RETURN_GENERATOR                
                                2       POP_TOP                         
                                4       RESUME                          0
                                6       LOAD_FAST                       0: .0
                                8       FOR_ITER                        14 (to 38)
                                12      UNPACK_SEQUENCE                 2
                                16      STORE_FAST                      1: n
                                18      STORE_FAST                      2: t
                                20      LOAD_CONST                      0: 'language_model.'
                                22      LOAD_FAST                       1: n
                                24      BINARY_OP                       0 (+)
                                28      LOAD_FAST                       2: t
                                30      BUILD_TUPLE                     2
                                32      YIELD_VALUE                     1
                                34      RESUME                          1
                                36      POP_TOP                         
                                38      JUMP_BACKWARD                   16 (to 8)
                                40      END_FOR                         
                                42      RETURN_CONST                    1: None
                                44      CALL_INTRINSIC_1                3 (INTRINSIC_STOPITERATION_ERROR)
                                46      RERAISE                         1
                            [Exception Table]
                                4 to 44 -> 44 [0] lasti
                    [Disassembly]
                        0       RESUME                          0
                        2       BUILD_MAP                       0
                        4       STORE_FAST                      2: perception_weights
                        6       LOAD_CONST                      1: 'perception.'
                        8       STORE_FAST                      3: perception_prefix
                        10      BUILD_LIST                      0
                        12      STORE_FAST                      4: llm_raw
                        14      LOAD_FAST                       1: weights
                        16      GET_ITER                        
                        18      FOR_ITER                        66 (to 152)
                        22      UNPACK_SEQUENCE                 2
                        26      STORE_FAST                      5: name
                        28      STORE_FAST                      6: tensor
                        30      LOAD_CONST                      2: '._extra_state'
                        32      LOAD_FAST                       5: name
                        34      CONTAINS_OP                     0 (in)
                        36      POP_JUMP_IF_FALSE               1 (to 40)
                        38      JUMP_BACKWARD                   11 (to 18)
                        40      LOAD_FAST                       5: name
                        42      LOAD_ATTR                       1: startswith
                        62      LOAD_FAST                       3: perception_prefix
                        64      CALL                            1
                        72      POP_JUMP_IF_FALSE               20 (to 114)
                        74      LOAD_FAST                       5: name
                        76      LOAD_GLOBAL                     3: NULL + len
                        86      LOAD_FAST                       3: perception_prefix
                        88      CALL                            1
                        96      LOAD_CONST                      0: None
                        98      BINARY_SLICE                    
                        100     STORE_FAST                      7: key
                        102     LOAD_FAST                       6: tensor
                        104     LOAD_FAST                       2: perception_weights
                        106     LOAD_FAST                       7: key
                        108     STORE_SUBSCR                    
                        112     JUMP_BACKWARD                   48 (to 18)
                        114     LOAD_FAST                       4: llm_raw
                        116     LOAD_ATTR                       5: append
                        136     LOAD_FAST                       5: name
                        138     LOAD_FAST                       6: tensor
                        140     BUILD_TUPLE                     2
                        142     CALL                            1
                        150     POP_TOP                         
                        152     JUMP_BACKWARD                   68 (to 18)
                        154     END_FOR                         
                        156     LOAD_FAST                       2: perception_weights
                        158     LOAD_ATTR                       7: items
                        178     CALL                            0
                        186     GET_ITER                        
                        188     LOAD_FAST_AND_CLEAR             8: k
                        190     LOAD_FAST_AND_CLEAR             9: v
                        192     SWAP                            3
                        194     BUILD_MAP                       0
                        196     SWAP                            2
                        198     FOR_ITER                        22 (to 244)
                        202     UNPACK_SEQUENCE                 2
                        206     STORE_FAST                      8: k
                        208     STORE_FAST                      9: v
                        210     LOAD_FAST                       8: k
                        212     LOAD_FAST                       9: v
                        214     LOAD_ATTR                       9: float
                        234     CALL                            0
                        242     MAP_ADD                         2
                        244     JUMP_BACKWARD                   24 (to 198)
                        246     END_FOR                         
                        248     STORE_FAST                      10: float32_weights
                        250     STORE_FAST                      8: k
                        252     STORE_FAST                      9: v
                        254     LOAD_FAST                       0: self
                        256     LOAD_ATTR                       10: perception
                        276     LOAD_ATTR                       13: load_state_dict
                        296     LOAD_FAST                       10: float32_weights
                        298     LOAD_CONST                      3: False
                        300     KW_NAMES                        4: ('strict',)
                        302     CALL                            2
                        310     POP_TOP                         
                        312     LOAD_FAST                       0: self
                        314     LOAD_ATTR                       10: perception
                        334     LOAD_ATTR                       15: to
                        354     LOAD_GLOBAL                     16: torch
                        364     LOAD_ATTR                       18: float32
                        384     CALL                            1
                        392     LOAD_FAST                       0: self
                        394     STORE_ATTR                      5: perception
                        404     LOAD_FAST                       2: perception_weights
                        406     GET_ITER                        
                        408     LOAD_FAST_AND_CLEAR             8: k
                        410     SWAP                            2
                        412     BUILD_SET                       0
                        414     SWAP                            2
                        416     FOR_ITER                        7 (to 432)
                        420     STORE_FAST                      8: k
                        422     LOAD_FAST                       3: perception_prefix
                        424     LOAD_FAST                       8: k
                        426     BINARY_OP                       0 (+)
                        430     SET_ADD                         2
                        432     JUMP_BACKWARD                   9 (to 416)
                        434     END_FOR                         
                        436     STORE_FAST                      11: loaded_perception
                        438     STORE_FAST                      8: k
                        440     LOAD_FAST                       0: self
                        442     LOAD_ATTR                       21: _nemo_to_hf_llm_weights
                        462     LOAD_FAST                       4: llm_raw
                        464     CALL                            1
                        472     STORE_FAST                      12: hf_weights
                        474     LOAD_CONST                      5: <CODE> <genexpr>
                        476     MAKE_FUNCTION                   0
                        478     LOAD_FAST                       12: hf_weights
                        480     GET_ITER                        
                        482     CALL                            0
                        490     STORE_FAST                      13: combined
                        492     LOAD_GLOBAL                     23: NULL + AutoWeightsLoader
                        502     LOAD_FAST                       0: self
                        504     CALL                            1
                        512     STORE_FAST                      14: loader
                        514     LOAD_FAST                       14: loader
                        516     LOAD_ATTR                       25: load_weights
                        536     LOAD_FAST                       13: combined
                        538     CALL                            1
                        546     STORE_FAST                      15: loaded_llm
                        548     LOAD_FAST                       15: loaded_llm
                        550     LOAD_FAST                       11: loaded_perception
                        552     BINARY_OP                       7 (|)
                        556     RETURN_VALUE                    
                        558     SWAP                            2
                        560     POP_TOP                         
                        562     SWAP                            3
                        564     STORE_FAST                      9: v
                        566     STORE_FAST                      8: k
                        568     RERAISE                         0
                        570     SWAP                            2
                        572     POP_TOP                         
                        574     SWAP                            2
                        576     STORE_FAST                      8: k
                        578     RERAISE                         0
                    [Exception Table]
                        194 to 248 -> 558 [3] 
                        412 to 436 -> 570 [2] 
                (
                    None
                    None
                )
            [Disassembly]
                0       MAKE_CELL                       0: __class__
                2       RESUME                          0
                4       LOAD_NAME                       0: __name__
                6       STORE_NAME                      1: __module__
                8       LOAD_CONST                      0: 'NeMoSpeechLMForConditionalGeneration'
                10      STORE_NAME                      2: __qualname__
                12      LOAD_CONST                      1: 'NeMo Speech LM model for vLLM inference.\n\n    Combines a NeMo speech encoder (AudioPerceptionModule) with a vLLM-native\n    LLM backbone (e.g. NemotronH).  Audio is encoded to embeddings that replace\n    placeholder tokens in the text sequence before LLM decoding.\n    '
                14      STORE_NAME                      3: __doc__
                16      LOAD_NAME                       4: classmethod
                18      LOAD_CONST                      2: 'modality'
                20      LOAD_NAME                       5: str
                22      LOAD_CONST                      3: 'i'
                24      LOAD_NAME                       6: int
                26      LOAD_CONST                      4: 'return'
                28      LOAD_NAME                       5: str
                30      LOAD_CONST                      5: None
                32      BINARY_OP                       7 (|)
                36      BUILD_TUPLE                     6
                38      LOAD_CONST                      6: <CODE> get_placeholder_str
                40      MAKE_FUNCTION                   4
                42      CALL                            0
                50      STORE_NAME                      7: get_placeholder_str
                52      LOAD_NAME                       4: classmethod
                54      LOAD_CONST                      7: <CODE> get_mamba_state_dtype_from_config
                56      MAKE_FUNCTION                   0
                58      CALL                            0
                66      STORE_NAME                      8: get_mamba_state_dtype_from_config
                68      LOAD_NAME                       4: classmethod
                70      LOAD_CONST                      8: <CODE> get_mamba_state_shape_from_config
                72      MAKE_FUNCTION                   0
                74      CALL                            0
                82      STORE_NAME                      9: get_mamba_state_shape_from_config
                84      LOAD_NAME                       4: classmethod
                86      LOAD_CONST                      9: <CODE> get_mamba_state_copy_func
                88      MAKE_FUNCTION                   0
                90      CALL                            0
                98      STORE_NAME                      10: get_mamba_state_copy_func
                100     LOAD_CONST                      10: ''
                102     LOAD_CONST                      11: ('prefix',)
                104     BUILD_CONST_KEY_MAP             1
                106     LOAD_CONST                      12: 'vllm_config'
                108     LOAD_NAME                       11: VllmConfig
                110     LOAD_CONST                      13: 'prefix'
                112     LOAD_NAME                       5: str
                114     BUILD_TUPLE                     4
                116     LOAD_CLOSURE                    0: __class__
                118     BUILD_TUPLE                     1
                120     LOAD_CONST                      14: <CODE> __init__
                122     MAKE_FUNCTION                   14
                124     STORE_NAME                      12: __init__
                126     LOAD_CONST                      4: 'return'
                128     LOAD_NAME                       13: NeMoSpeechLMAudioInputs
                130     LOAD_CONST                      5: None
                132     BINARY_OP                       7 (|)
                136     BUILD_TUPLE                     2
                138     LOAD_CONST                      15: <CODE> _parse_audio_input
                140     MAKE_FUNCTION                   4
                142     STORE_NAME                      14: _parse_audio_input
                144     LOAD_CONST                      16: 'audio_input'
                146     LOAD_NAME                       13: NeMoSpeechLMAudioInputs
                148     LOAD_CONST                      4: 'return'
                150     LOAD_NAME                       15: tuple
                152     LOAD_NAME                       16: torch
                154     LOAD_ATTR                       34: Tensor
                174     LOAD_CONST                      17: ...
                176     BUILD_TUPLE                     2
                178     BINARY_SUBSCR                   
                182     BUILD_TUPLE                     4
                184     LOAD_CONST                      18: <CODE> _process_audio
                186     MAKE_FUNCTION                   4
                188     STORE_NAME                      18: _process_audio
                190     LOAD_CONST                      4: 'return'
                192     LOAD_NAME                       19: MultiModalEmbeddings
                194     BUILD_TUPLE                     2
                196     LOAD_CONST                      19: <CODE> embed_multimodal
                198     MAKE_FUNCTION                   4
                200     STORE_NAME                      20: embed_multimodal
                202     NOP                             
                204     NOP                             
                206     LOAD_CONST                      31: (None, None)
                208     LOAD_CONST                      20: 'input_ids'
                210     LOAD_NAME                       16: torch
                212     LOAD_ATTR                       34: Tensor
                232     LOAD_CONST                      21: 'positions'
                234     LOAD_NAME                       16: torch
                236     LOAD_ATTR                       34: Tensor
                256     LOAD_CONST                      22: 'intermediate_tensors'
                258     LOAD_NAME                       21: IntermediateTensors
                260     LOAD_CONST                      5: None
                262     BINARY_OP                       7 (|)
                266     LOAD_CONST                      23: 'inputs_embeds'
                268     LOAD_NAME                       16: torch
                270     LOAD_ATTR                       34: Tensor
                290     LOAD_CONST                      5: None
                292     BINARY_OP                       7 (|)
                296     LOAD_CONST                      4: 'return'
                298     LOAD_NAME                       16: torch
                300     LOAD_ATTR                       34: Tensor
                320     LOAD_NAME                       21: IntermediateTensors
                322     BINARY_OP                       7 (|)
                326     BUILD_TUPLE                     10
                328     LOAD_CONST                      24: <CODE> forward
                330     MAKE_FUNCTION                   5
                332     STORE_NAME                      22: forward
                334     LOAD_CONST                      25: 'hidden_states'
                336     LOAD_NAME                       16: torch
                338     LOAD_ATTR                       34: Tensor
                358     LOAD_CONST                      4: 'return'
                360     LOAD_NAME                       16: torch
                362     LOAD_ATTR                       34: Tensor
                382     LOAD_CONST                      5: None
                384     BINARY_OP                       7 (|)
                388     BUILD_TUPLE                     4
                390     LOAD_CONST                      26: <CODE> compute_logits
                392     MAKE_FUNCTION                   4
                394     STORE_NAME                      23: compute_logits
                396     LOAD_CONST                      4: 'return'
                398     LOAD_NAME                       24: MultiModelKeys
                400     BUILD_TUPLE                     2
                402     LOAD_CONST                      27: <CODE> get_mm_mapping
                404     MAKE_FUNCTION                   4
                406     STORE_NAME                      25: get_mm_mapping
                408     LOAD_CONST                      28: 'weights'
                410     LOAD_NAME                       26: Iterable
                412     LOAD_NAME                       15: tuple
                414     LOAD_NAME                       5: str
                416     LOAD_NAME                       16: torch
                418     LOAD_ATTR                       34: Tensor
                438     BUILD_TUPLE                     2
                440     BINARY_SUBSCR                   
                444     BINARY_SUBSCR                   
                448     LOAD_CONST                      4: 'return'
                450     LOAD_NAME                       26: Iterable
                452     LOAD_NAME                       15: tuple
                454     LOAD_NAME                       5: str
                456     LOAD_NAME                       16: torch
                458     LOAD_ATTR                       34: Tensor
                478     BUILD_TUPLE                     2
                480     BINARY_SUBSCR                   
                484     BINARY_SUBSCR                   
                488     BUILD_TUPLE                     4
                490     LOAD_CONST                      29: <CODE> _nemo_to_hf_llm_weights
                492     MAKE_FUNCTION                   4
                494     STORE_NAME                      27: _nemo_to_hf_llm_weights
                496     LOAD_CONST                      28: 'weights'
                498     LOAD_NAME                       26: Iterable
                500     LOAD_NAME                       15: tuple
                502     LOAD_NAME                       5: str
                504     LOAD_NAME                       16: torch
                506     LOAD_ATTR                       34: Tensor
                526     BUILD_TUPLE                     2
                528     BINARY_SUBSCR                   
                532     BINARY_SUBSCR                   
                536     LOAD_CONST                      4: 'return'
                538     LOAD_NAME                       28: set
                540     LOAD_NAME                       5: str
                542     BINARY_SUBSCR                   
                546     BUILD_TUPLE                     4
                548     LOAD_CONST                      30: <CODE> load_weights
                550     MAKE_FUNCTION                   4
                552     STORE_NAME                      29: load_weights
                554     LOAD_CLOSURE                    0: __class__
                556     COPY                            1
                558     STORE_NAME                      30: __classcell__
                560     RETURN_VALUE                    
            [Exception Table]
        'NeMoSpeechLMForConditionalGeneration'
        (
            None
        )
    [Disassembly]
        0       RESUME                          0
        2       LOAD_CONST                      0: 'Inference-only NeMo Speech LM model for vLLM.\n\nArchitecture: NeMo speech encoder (e.g. FastConformer) + projection + LLM backbone\n(e.g. NemotronH).  Requires NeMo toolkit for the audio encoder:\n``pip install nemo_toolkit[asr]``\n'
        4       STORE_NAME                      0: __doc__
        6       LOAD_CONST                      1: 0
        8       LOAD_CONST                      2: None
        10      IMPORT_NAME                     1: re
        12      STORE_NAME                      1: re
        14      LOAD_CONST                      1: 0
        16      LOAD_CONST                      3: ('Iterable', 'Mapping')
        18      IMPORT_NAME                     2: collections.abc
        20      IMPORT_FROM                     3: Iterable
        22      STORE_NAME                      3: Iterable
        24      IMPORT_FROM                     4: Mapping
        26      STORE_NAME                      4: Mapping
        28      POP_TOP                         
        30      LOAD_CONST                      1: 0
        32      LOAD_CONST                      4: ('Annotated', 'Literal')
        34      IMPORT_NAME                     5: typing
        36      IMPORT_FROM                     6: Annotated
        38      STORE_NAME                      6: Annotated
        40      IMPORT_FROM                     7: Literal
        42      STORE_NAME                      7: Literal
        44      POP_TOP                         
        46      LOAD_CONST                      1: 0
        48      LOAD_CONST                      2: None
        50      IMPORT_NAME                     8: torch
        52      STORE_NAME                      8: torch
        54      LOAD_CONST                      1: 0
        56      LOAD_CONST                      5: ('nn',)
        58      IMPORT_NAME                     8: torch
        60      IMPORT_FROM                     9: nn
        62      STORE_NAME                      9: nn
        64      POP_TOP                         
        66      LOAD_CONST                      1: 0
        68      LOAD_CONST                      6: ('BatchFeature',)
        70      IMPORT_NAME                     10: transformers
        72      IMPORT_FROM                     11: BatchFeature
        74      STORE_NAME                      11: BatchFeature
        76      POP_TOP                         
        78      LOAD_CONST                      1: 0
        80      LOAD_CONST                      7: ('VllmConfig',)
        82      IMPORT_NAME                     12: vllm.config
        84      IMPORT_FROM                     13: VllmConfig
        86      STORE_NAME                      13: VllmConfig
        88      POP_TOP                         
        90      LOAD_CONST                      1: 0
        92      LOAD_CONST                      8: ('BaseDummyOptions',)
        94      IMPORT_NAME                     14: vllm.config.multimodal
        96      IMPORT_FROM                     15: BaseDummyOptions
        98      STORE_NAME                      15: BaseDummyOptions
        100     POP_TOP                         
        102     LOAD_CONST                      1: 0
        104     LOAD_CONST                      9: ('IsHybrid', 'MultiModalEmbeddings', 'SupportsMambaPrefixCaching', 'SupportsMultiModal', 'SupportsPP')
        106     IMPORT_NAME                     16: vllm.model_executor.models.interfaces
        108     IMPORT_FROM                     17: IsHybrid
        110     STORE_NAME                      17: IsHybrid
        112     IMPORT_FROM                     18: MultiModalEmbeddings
        114     STORE_NAME                      18: MultiModalEmbeddings
        116     IMPORT_FROM                     19: SupportsMambaPrefixCaching
        118     STORE_NAME                      19: SupportsMambaPrefixCaching
        120     IMPORT_FROM                     20: SupportsMultiModal
        122     STORE_NAME                      20: SupportsMultiModal
        124     IMPORT_FROM                     21: SupportsPP
        126     STORE_NAME                      21: SupportsPP
        128     POP_TOP                         
        130     LOAD_CONST                      1: 0
        132     LOAD_CONST                      10: ('MultiModelKeys',)
        134     IMPORT_NAME                     22: vllm.model_executor.models.module_mapping
        136     IMPORT_FROM                     23: MultiModelKeys
        138     STORE_NAME                      23: MultiModelKeys
        140     POP_TOP                         
        142     LOAD_CONST                      1: 0
        144     LOAD_CONST                      11: ('AutoWeightsLoader', 'init_vllm_registered_model', 'maybe_prefix')
        146     IMPORT_NAME                     24: vllm.model_executor.models.utils
        148     IMPORT_FROM                     25: AutoWeightsLoader
        150     STORE_NAME                      25: AutoWeightsLoader
        152     IMPORT_FROM                     26: init_vllm_registered_model
        154     STORE_NAME                      26: init_vllm_registered_model
        156     IMPORT_FROM                     27: maybe_prefix
        158     STORE_NAME                      27: maybe_prefix
        160     POP_TOP                         
        162     LOAD_CONST                      1: 0
        164     LOAD_CONST                      12: ('MULTIMODAL_REGISTRY',)
        166     IMPORT_NAME                     28: vllm.multimodal
        168     IMPORT_FROM                     29: MULTIMODAL_REGISTRY
        170     STORE_NAME                      29: MULTIMODAL_REGISTRY
        172     POP_TOP                         
        174     LOAD_CONST                      1: 0
        176     LOAD_CONST                      13: ('MultiModalDataDict',)
        178     IMPORT_NAME                     30: vllm.inputs
        180     IMPORT_FROM                     31: MultiModalDataDict
        182     STORE_NAME                      31: MultiModalDataDict
        184     POP_TOP                         
        186     LOAD_CONST                      1: 0
        188     LOAD_CONST                      14: ('MultiModalFieldConfig', 'MultiModalKwargsItems')
        190     IMPORT_NAME                     32: vllm.multimodal.inputs
        192     IMPORT_FROM                     33: MultiModalFieldConfig
        194     STORE_NAME                      33: MultiModalFieldConfig
        196     IMPORT_FROM                     34: MultiModalKwargsItems
        198     STORE_NAME                      34: MultiModalKwargsItems
        200     POP_TOP                         
        202     LOAD_CONST                      1: 0
        204     LOAD_CONST                      15: ('AudioProcessorItems', 'MultiModalDataItems', 'MultiModalDataParser')
        206     IMPORT_NAME                     35: vllm.multimodal.parse
        208     IMPORT_FROM                     36: AudioProcessorItems
        210     STORE_NAME                      36: AudioProcessorItems
        212     IMPORT_FROM                     37: MultiModalDataItems
        214     STORE_NAME                      37: MultiModalDataItems
        216     IMPORT_FROM                     38: MultiModalDataParser
        218     STORE_NAME                      38: MultiModalDataParser
        220     POP_TOP                         
        222     LOAD_CONST                      1: 0
        224     LOAD_CONST                      16: ('BaseMultiModalProcessor', 'BaseProcessingInfo', 'PromptReplacement', 'PromptUpdate', 'PromptUpdateDetails')
        226     IMPORT_NAME                     39: vllm.multimodal.processing
        228     IMPORT_FROM                     40: BaseMultiModalProcessor
        230     STORE_NAME                      40: BaseMultiModalProcessor
        232     IMPORT_FROM                     41: BaseProcessingInfo
        234     STORE_NAME                      41: BaseProcessingInfo
        236     IMPORT_FROM                     42: PromptReplacement
        238     STORE_NAME                      42: PromptReplacement
        240     IMPORT_FROM                     43: PromptUpdate
        242     STORE_NAME                      43: PromptUpdate
        244     IMPORT_FROM                     44: PromptUpdateDetails
        246     STORE_NAME                      44: PromptUpdateDetails
        248     POP_TOP                         
        250     LOAD_CONST                      1: 0
        252     LOAD_CONST                      17: ('BaseDummyInputsBuilder',)
        254     IMPORT_NAME                     45: vllm.multimodal.processing.dummy_inputs
        256     IMPORT_FROM                     46: BaseDummyInputsBuilder
        258     STORE_NAME                      46: BaseDummyInputsBuilder
        260     POP_TOP                         
        262     LOAD_CONST                      1: 0
        264     LOAD_CONST                      18: ('IntermediateTensors',)
        266     IMPORT_NAME                     47: vllm.sequence
        268     IMPORT_FROM                     48: IntermediateTensors
        270     STORE_NAME                      48: IntermediateTensors
        272     POP_TOP                         
        274     LOAD_CONST                      1: 0
        276     LOAD_CONST                      19: ('TensorSchema', 'TensorShape')
        278     IMPORT_NAME                     49: vllm.utils.tensor_schema
        280     IMPORT_FROM                     50: TensorSchema
        282     STORE_NAME                      50: TensorSchema
        284     IMPORT_FROM                     51: TensorShape
        286     STORE_NAME                      51: TensorShape
        288     POP_TOP                         
        290     LOAD_CONST                      20: '<|audio|>'
        292     STORE_NAME                      52: _AUDIO_PLACEHOLDER
        294     LOAD_CONST                      21: 16000
        296     STORE_NAME                      53: _SAMPLING_RATE
        298     LOAD_CONST                      22: 40
        300     STORE_NAME                      54: _MAX_AUDIO_DURATION_S
        302     LOAD_CONST                      23: <CODE> _ensure_special_tokens
        304     MAKE_FUNCTION                   0
        306     STORE_NAME                      55: _ensure_special_tokens
        308     LOAD_CONST                      24: 'perception'
        310     LOAD_NAME                       9: nn
        312     LOAD_ATTR                       112: Module
        332     LOAD_CONST                      25: 'pe_encoder_path'
        334     LOAD_NAME                       57: str
        336     LOAD_CONST                      26: 'return'
        338     LOAD_CONST                      2: None
        340     BUILD_TUPLE                     6
        342     LOAD_CONST                      27: <CODE> _mount_parallel_expert_encoder
        344     MAKE_FUNCTION                   4
        346     STORE_NAME                      58: _mount_parallel_expert_encoder
        348     NOP                             
        350     LOAD_CONST                      42: (None,)
        352     LOAD_CONST                      28: 'perception_cfg'
        354     LOAD_NAME                       59: dict
        356     LOAD_CONST                      29: 'output_dim'
        358     LOAD_NAME                       60: int
        360     LOAD_CONST                      25: 'pe_encoder_path'
        362     LOAD_NAME                       57: str
        364     LOAD_CONST                      2: None
        366     BINARY_OP                       7 (|)
        370     LOAD_CONST                      26: 'return'
        372     LOAD_NAME                       9: nn
        374     LOAD_ATTR                       112: Module
        394     BUILD_TUPLE                     8
        396     LOAD_CONST                      30: <CODE> _load_nemo_perception
        398     MAKE_FUNCTION                   5
        400     STORE_NAME                      61: _load_nemo_perception
        402     PUSH_NULL                       
        404     LOAD_BUILD_CLASS                
        406     LOAD_CONST                      31: <CODE> NeMoSpeechLMAudioInputs
        408     MAKE_FUNCTION                   0
        410     LOAD_CONST                      32: 'NeMoSpeechLMAudioInputs'
        412     LOAD_NAME                       50: TensorSchema
        414     CALL                            3
        422     STORE_NAME                      62: NeMoSpeechLMAudioInputs
        424     PUSH_NULL                       
        426     LOAD_BUILD_CLASS                
        428     LOAD_CONST                      33: <CODE> NeMoSpeechLMProcessingInfo
        430     MAKE_FUNCTION                   0
        432     LOAD_CONST                      34: 'NeMoSpeechLMProcessingInfo'
        434     LOAD_NAME                       41: BaseProcessingInfo
        436     CALL                            3
        444     STORE_NAME                      63: NeMoSpeechLMProcessingInfo
        446     PUSH_NULL                       
        448     LOAD_BUILD_CLASS                
        450     LOAD_CONST                      35: <CODE> NeMoSpeechLMMultiModalProcessor
        452     MAKE_FUNCTION                   0
        454     LOAD_CONST                      36: 'NeMoSpeechLMMultiModalProcessor'
        456     LOAD_NAME                       40: BaseMultiModalProcessor
        458     LOAD_NAME                       63: NeMoSpeechLMProcessingInfo
        460     BINARY_SUBSCR                   
        464     CALL                            3
        472     STORE_NAME                      64: NeMoSpeechLMMultiModalProcessor
        474     PUSH_NULL                       
        476     LOAD_BUILD_CLASS                
        478     LOAD_CONST                      37: <CODE> NeMoSpeechLMDummyInputsBuilder
        480     MAKE_FUNCTION                   0
        482     LOAD_CONST                      38: 'NeMoSpeechLMDummyInputsBuilder'
        484     LOAD_NAME                       46: BaseDummyInputsBuilder
        486     LOAD_NAME                       63: NeMoSpeechLMProcessingInfo
        488     BINARY_SUBSCR                   
        492     CALL                            3
        500     STORE_NAME                      65: NeMoSpeechLMDummyInputsBuilder
        502     PUSH_NULL                       
        504     LOAD_NAME                       29: MULTIMODAL_REGISTRY
        506     LOAD_ATTR                       132: register_processor
        526     LOAD_NAME                       64: NeMoSpeechLMMultiModalProcessor
        528     LOAD_NAME                       63: NeMoSpeechLMProcessingInfo
        530     LOAD_NAME                       65: NeMoSpeechLMDummyInputsBuilder
        532     KW_NAMES                        39: ('info', 'dummy_inputs')
        534     CALL                            3
        542     PUSH_NULL                       
        544     LOAD_BUILD_CLASS                
        546     LOAD_CONST                      40: <CODE> NeMoSpeechLMForConditionalGeneration
        548     MAKE_FUNCTION                   0
        550     LOAD_CONST                      41: 'NeMoSpeechLMForConditionalGeneration'
        552     LOAD_NAME                       9: nn
        554     LOAD_ATTR                       112: Module
        574     LOAD_NAME                       20: SupportsMultiModal
        576     LOAD_NAME                       21: SupportsPP
        578     LOAD_NAME                       17: IsHybrid
        580     LOAD_NAME                       19: SupportsMambaPrefixCaching
        582     CALL                            7
        590     CALL                            0
        598     STORE_NAME                      67: NeMoSpeechLMForConditionalGeneration
        600     RETURN_CONST                    2: None
    [Exception Table]
